Workbook

Sheet Overview
A1: GATE CSE 2027 – 12-Week Crash Plan (13 Oct → 31 Dec 2026)
A2: Goal: cover 6 of the 10 GATE sections by 31 Dec (Engineering Maths every day + 5 core subjects) while preparing for IPU end-terms. January = PYQs only.
A4: 1. Key dates
A5: Practical exams (5th sem) | B5: 26 Nov – 6 Dec 2026 (load reduced to 2.5 h/day)
A6: Theory exams (all 2–5 PM) | B6: 15 Dec DAA (CIC-311) · 17 Dec Compiler Design (CIC-303) · 19 Dec OS (CIC-305) · 22 Dec Computer Networks (CIC-307) · 24 Dec Software Engineering (CIC-309) · 28 Dec Economics (HS-301)
A7: GATE 2027 | B7: Early February 2027 (check the official IIT Madras date)
A9: 2. How a day works (Mon–Sat)
A10: 1. Easy start (15–20 min) | B10: Aptitude (15 of 100 GATE marks): 8–10 easy questions. Verbal topics → GATE Overflow verbal lessons; quant/reasoning → Saurabh Thakur's aptitude course (see Playlist Directory).
A11: 2. ONE maths lecture (30–40 min) | B11: Exactly one Engineering Maths lecture a day: Discrete (22 days) → Linear Algebra (7) → Probability & Statistics (12) → Calculus (9) → 2 PYQ days.
A12: 3. Main subject lecture (55–75 min) | B12: The day's topic from the subject sheet. Watch at 1.25x–1.5x and make short notes.
A13: 4. PYQ practice (20–45 min) | B13: PYQs on exactly that topic from GO-PDFs. Do not skip this.
A14: Ramp-up | B14: Week 1 (13–17 Oct) = 2 h/day, week 2 = 2.5 h/day, from 26 Oct = 3 h/day. Practical window = 2.5 h. Sundays = revision + timed test (subjects + maths).
A16: 3. What's covered by 31 Dec (60% of sections)
A17: Included (6 sections) | B17: Engineering Maths (Discrete, Linear Algebra, Probability, Calculus), Programming & Data Structures, Algorithms, Compiler Design, Operating System, Computer Networks. Four of these are your IPU subjects, so one session serves GATE and university.
A18: Not included (4 sections) | B18: Digital Logic, COA, Theory of Computation, Databases → January, using the PYQ video-solution playlists as your learning source.
A19: Order | B19: Subjects: C → DS → Algorithms → Compiler Design → OS → Networks, so each is learned before its university exam and revised Dec 11–22.
A21: 4. Sheets in this workbook
A22: Progress | B22: Auto % complete per subject, maths and aptitude + overall GATE coverage.
A23: Master Planner | B23: Every day 13 Oct – 31 Dec: subject, maths lecture, time split.
A24: 1–6 subject sheets | B24: Per day: main lecture (+ maths/aptitude shown for reference), playlist title · teacher (clickable), video search links, textbook, PYQs, and a Status for that subject only.
A25: 7 Engineering Maths | B25: The 52 daily maths lectures with playlist, teacher, search links and its own Status.
A26: 8 Aptitude | B26: Daily aptitude topics in 4 rounds (learn → practice → timed → full sets) with its own Status.
A27: Sunday Revision / Uni Exams & Wrap-up | B27: Weekly revision with the week's topics auto-listed; Dec 11–31 exam prep and GATE recap.
A28: Playlist Directory | B28: Every playlist with title, teacher/channel, uploader, video count and link.
A30: 5. Please read
A31: Video links | B31: YouTube does not let me read what is inside a playlist, so I could not verify an individual video URL for each topic and did not invent any. Instead every day has the verified playlist (title · teacher, clickable) plus a 'Search this lecture ▶' link that opens YouTube search for that exact topic with the teacher's name. If you paste a playlist's video titles into the chat, I can map each day to the exact video number.
A32: Teachers | B32: Names come from the playlist titles/owners. Where YouTube only shows a channel (e.g. GO Classes, NPTEL), that's what is written – no guessed names.
A33: Maths gaps | B33: Your PDF has no dedicated First-Order Logic, Relations, Functions or Posets/Lattices playlist. Days 4–5 and 7–11 use the closest listed playlists; the Notes column says what to search if a topic isn't there.
A34: Aptitude | B34: I verified GATE Overflow's verbal lessons (linked from GATE Overflow's own post) and Saurabh Thakur's aptitude course (Unacademy, not YouTube). I could not verify a YouTube quant playlist.
A35: Your subjects | B35: Confirmed: Software Engineering (CIC-309) is a subject this semester; DBMS is not, so it is left to January GATE study. Software Engineering and Economics syllabi were not shared, so Dec 23 & Dec 25–27 use typical topics – replace with your IPU units.
A36: Time check | B36: Adding a daily maths lecture trimmed the main lecture to 75 min (at 1.5x ≈ 110 min of video). If a day overruns, finish the main lecture and push the maths lecture to the next day's slot; Sundays absorb the slack.
A37: Status | B37: Each subject has its own Status: subject sheets 1–6 track only that subject, sheet 7 tracks Maths, sheet 8 tracks Aptitude. Done = green, In Progress = yellow. Progress updates automatically.
A38: Late start (13 Oct) | B38: Plan now starts on Tue 13 Oct instead of Mon 12 Oct. Every lecture moved one study-day later; Sundays, practicals and university exam dates did not move. The one lecture that no longer fits before 10 Dec is moved: CN Day 8 (Application layer) → 21 Dec, and Maths M52 + Aptitude Day 52 → 29 Dec.

Sheet Progress
A1: Progress Tracker (auto-updates from Status columns)
A3: Sheet | B3: Total study days | C3: Days marked Done | D3: % complete
A4: C Programming | B4: =COUNTA('1 C Programming'!A12:A16) -> 5 | C4: =COUNTIF('1 C Programming'!P12:P16,"Done") -> 0 | D4: =IF(B4=0,0,C4/B4) -> 0
A5: Data Structures | B5: =COUNTA('2 Data Structures'!A13:A21) -> 9 | C5: =COUNTIF('2 Data Structures'!P13:P21,"Done") -> 0 | D5: =IF(B5=0,0,C5/B5) -> 0
A6: Algorithms (DAA) | B6: =COUNTA('3 Algorithms DAA'!A13:A25) -> 13 | C6: =COUNTIF('3 Algorithms DAA'!P13:P25,"Done") -> 0 | D6: =IF(B6=0,0,C6/B6) -> 0
A7: Compiler Design | B7: =COUNTA('4 Compiler Design'!A14:A20) -> 7 | C7: =COUNTIF('4 Compiler Design'!P14:P20,"Done") -> 0 | D7: =IF(B7=0,0,C7/B7) -> 0
A8: Operating Systems | B8: =COUNTA('5 Operating Systems'!A13:A22) -> 10 | C8: =COUNTIF('5 Operating Systems'!P13:P22,"Done") -> 0 | D8: =IF(B8=0,0,C8/B8) -> 0
A9: Computer Networks | B9: =COUNTA('6 Computer Networks'!A13:A20) -> 8 | C9: =COUNTIF('6 Computer Networks'!P13:P20,"Done") -> 0 | D9: =IF(B9=0,0,C9/B9) -> 0
A10: Engineering Maths | B10: =COUNTA('7 Engineering Maths'!A5:A56) -> 52 | C10: =COUNTIF('7 Engineering Maths'!K5:K56,"Done") -> 0 | D10: =IF(B10=0,0,C10/B10) -> 0
A11: Aptitude | B11: =COUNTA('8 Aptitude'!A11:A62) -> 52 | C11: =COUNTIF('8 Aptitude'!J11:J62,"Done") -> 0 | D11: =IF(B11=0,0,C11/B11) -> 0
A12: Sunday revisions | B12: =COUNTA('Sunday Revision'!A5:A12) -> 8 | C12: =COUNTIF('Sunday Revision'!H5:H12,"Done") -> 0 | D12: =IF(B12=0,0,C12/B12) -> 0
A13: Uni exam prep & wrap-up days | B13: =COUNTA('Uni Exams & Wrap-up'!A5:A25) -> 21 | C13: =COUNTIF('Uni Exams & Wrap-up'!I5:I25,"Done") -> 0 | D13: =IF(B13=0,0,C13/B13) -> 0
A15: GATE 2027 syllabus coverage (10 sections, each weighted equally)
A16: GATE section | B16: Weight (assumed) | C16: Covered in this plan? | D16: Progress | E16: Contribution
A17: Engineering Mathematics | B17: 0.1 | C17: Yes | D17: =D10 -> 0 | E17: =B17*D17 -> 0
A18: Digital Logic | B18: 0.1 | C18: No – January (PYQs) | D18: 0 | E18: =B18*D18 -> 0
A19: Computer Organization & Architecture | B19: 0.1 | C19: No – January (PYQs) | D19: 0 | E19: =B19*D19 -> 0
A20: Programming & Data Structures | B20: 0.1 | C20: Yes | D20: =IF(B4+B5=0,0,(C4+C5)/(B4+B5)) -> 0 | E20: =B20*D20 -> 0
A21: Algorithms | B21: 0.1 | C21: Yes | D21: =D6 -> 0 | E21: =B21*D21 -> 0
A22: Theory of Computation | B22: 0.1 | C22: No – January (PYQs) | D22: 0 | E22: =B22*D22 -> 0
A23: Compiler Design | B23: 0.1 | C23: Yes | D23: =D7 -> 0 | E23: =B23*D23 -> 0
A24: Operating System | B24: 0.1 | C24: Yes | D24: =D8 -> 0 | E24: =B24*D24 -> 0
A25: Databases | B25: 0.1 | C25: No – January (PYQs) | D25: 0 | E25: =B25*D25 -> 0
A26: Computer Networks | B26: 0.1 | C26: Yes | D26: =D9 -> 0 | E26: =B26*D26 -> 0
A27: TOTAL GATE SYLLABUS COMPLETED | B27: =SUM(B17:B26) -> 1 | E27: =SUM(E17:E26) -> 0
A29: Weights are an assumption (equal share per section; blue = editable). With daily maths, 6 of 10 sections are covered, so the ceiling by 31 Dec is 60%.

Sheet Master Planner
A1: Master Planner – 13 Oct to 31 Dec 2026 (every day)
A2: Read-only calendar. Tick progress in the subject sheets / Maths sheet (Status column).
A4: Date | B4: Day | C4: Type | D4: Subject | E4: Main focus | F4: Maths lecture (1/day) | G4: Easy start (min) | H4: Maths (min) | I4: Main block (min) | J4: Practice / test (min) | K4: Total (hrs) | L4: Note
A5: 46308 | B5: =TEXT(A5,"ddd") -> Tue | C5: GATE learning | D5: C Programming | E5: Day 1: Basics: data types, operators, precedence | F5: M1: Propositional logic I: propositions, connectives, truth tables | G5: 15 | H5: 30 | I5: 55 | J5: 20 | K5: =(G5+H5+I5+J5)/60 -> 2
A6: 46309 | B6: =TEXT(A6,"ddd") -> Wed | C6: GATE learning | D6: C Programming | E6: Day 2: Control flow & I/O | F6: M2: Propositional logic II: equivalences, tautology, normal forms | G6: 15 | H6: 30 | I6: 55 | J6: 20 | K6: =(G6+H6+I6+J6)/60 -> 2
A7: 46310 | B7: =TEXT(A7,"ddd") -> Thu | C7: GATE learning | D7: C Programming | E7: Day 3: Functions, recursion & storage classes | F7: M3: Propositional logic III: inference, validity, functional completeness | G7: 15 | H7: 30 | I7: 55 | J7: 20 | K7: =(G7+H7+I7+J7)/60 -> 2
A8: 46311 | B8: =TEXT(A8,"ddd") -> Fri | C8: GATE learning | D8: C Programming | E8: Day 4: Arrays, strings & pointer basics | F8: M4: First-order logic I: predicates & quantifiers | G8: 15 | H8: 30 | I8: 55 | J8: 20 | K8: =(G8+H8+I8+J8)/60 -> 2
A9: 46312 | B9: =TEXT(A9,"ddd") -> Sat | C9: GATE learning | D9: C Programming | E9: Day 5: Advanced pointers, structs, unions, malloc, macros | F9: M5: First-order logic II: translation & nested quantifiers | G9: 15 | H9: 30 | I9: 55 | J9: 20 | K9: =(G9+H9+I9+J9)/60 -> 2
A10: 46313 | B10: =TEXT(A10,"ddd") -> Sun | C10: Weekly revision + test | D10: Revision | E10: Revise the week's topics (incl. maths), timed PYQ test, error log | F10: Maths revision inside the test | G10: 30 | H10: 0 | I10: 90 | J10: 60 | K10: =(G10+H10+I10+J10)/60 -> 3
A11: 46314 | B11: =TEXT(A11,"ddd") -> Mon | C11: GATE learning | D11: Data Structures | E11: Day 1: Arrays & singly linked list | F11: M6: Sets: operations, power set, cardinality | G11: 20 | H11: 35 | I11: 65 | J11: 30 | K11: =(G11+H11+I11+J11)/60 -> 2.5
A12: 46315 | B12: =TEXT(A12,"ddd") -> Tue | C12: GATE learning | D12: Data Structures | E12: Day 2: Doubly/circular linked list & stacks | F12: M7: Relations I: types & representation | G12: 20 | H12: 35 | I12: 65 | J12: 30 | K12: =(G12+H12+I12+J12)/60 -> 2.5
A13: 46316 | B13: =TEXT(A13,"ddd") -> Wed | C13: GATE learning | D13: Data Structures | E13: Day 3: Expression conversion, queues & deque | F13: M8: Relations II: equivalence relations, partitions, closures | G13: 20 | H13: 35 | I13: 65 | J13: 30 | K13: =(G13+H13+I13+J13)/60 -> 2.5
A14: 46317 | B14: =TEXT(A14,"ddd") -> Thu | C14: GATE learning | D14: Data Structures | E14: Day 4: Binary trees & traversals | F14: M9: Functions: injective, surjective, bijective | G14: 20 | H14: 35 | I14: 65 | J14: 30 | K14: =(G14+H14+I14+J14)/60 -> 2.5
A15: 46318 | B15: =TEXT(A15,"ddd") -> Fri | C15: GATE learning | D15: Data Structures | E15: Day 5: BST & AVL trees | F15: M10: Partial orders & Hasse diagrams | G15: 20 | H15: 35 | I15: 65 | J15: 30 | K15: =(G15+H15+I15+J15)/60 -> 2.5
A16: 46319 | B16: =TEXT(A16,"ddd") -> Sat | C16: GATE learning | D16: Data Structures | E16: Day 6: Binary heaps & priority queue | F16: M11: Lattices | G16: 20 | H16: 35 | I16: 65 | J16: 30 | K16: =(G16+H16+I16+J16)/60 -> 2.5
... A30: 46333 | B30: =TEXT(A30,"ddd") -> Sat | C30: GATE + Uni learning | D30: Algorithms (DAA) | E30: Day 9: Minimum spanning trees & union-find | F30: M23: Matrices: types & operations | G30: 20 | H30: 40 | I30: 75 | J30: 45 | K30: =(G30+H30+I30+J30)/60 -> 3
A31: 46334 | B31: =TEXT(A31,"ddd") -> Sun | C31: Weekly revision + test | D31: Revision | E31: Diwali (approx.) – light day: only error-log review | G31: 20 | H31: 0 | I31: 0 | J31: 40 | K31: =(G31+H31+I31+J31)/60 -> 1 | L31: Festival – keep it light
A32: 46335 | B32: =TEXT(A32,"ddd") -> Mon | C32: GATE + Uni learning | D32: Algorithms (DAA) | E32: Day 10: Shortest paths | F32: M24: Determinants | G32: 20 | H32: 40 | I32: 75 | J32: 45 | K32: =(G32+H32+I32+J32)/60 -> 3
A33: 46336 | B33: =TEXT(A33,"ddd") -> Tue | C33: GATE + Uni learning | D33: Algorithms (DAA) | E33: Day 11: Dynamic programming I | F33: M25: Rank & inverse | G33: 20 | H33: 40 | I33: 75 | J33: 45 | K33: =(G33+H33+I33+J33)/60 -> 3
A34: 46337 | B34: =TEXT(A34,"ddd") -> Wed | C34: GATE + Uni learning | D34: Algorithms (DAA) | E34: Day 12: Dynamic programming II | F34: M26: Systems of linear equations | G34: 20 | H34: 40 | I34: 75 | J34: 45 | K34: =(G34+H34+I34+J34)/60 -> 3
A35: 46338 | B35: =TEXT(A35,"ddd") -> Thu | C35: GATE + Uni learning | D35: Algorithms (DAA) | E35: Day 13: Uni-only: backtracking, branch & bound, NP-completeness | F35: M27: Eigenvalues & eigenvectors | G35: 20 | H35: 40 | I35: 75 | J35: 45 | K35: =(G35+H35+I35+J35)/60 -> 3
A36: 46339 | B36: =TEXT(A36,"ddd") -> Fri | C36: GATE + Uni learning | D36: Compiler Design | E36: Day 1: Compiler phases & lexical analysis | F36: M28: Eigen properties: Cayley-Hamilton & diagonalisation | G36: 20 | H36: 40 | I36: 75 | J36: 45 | K36: =(G36+H36+I36+J36)/60 -> 3
A37: 46340 | B37: =TEXT(A37,"ddd") -> Sat | C37: GATE + Uni learning | D37: Compiler Design | E37: Day 2: Parsing I: top-down & LL(1) | F37: M29: LU decomposition + LA problem-solving | G37: 20 | H37: 40 | I37: 75 | J37: 45 | K37: =(G37+H37+I37+J37)/60 -> 3
A38: 46341 | B38: =TEXT(A38,"ddd") -> Sun | C38: Weekly revision + test | D38: Revision | E38: Revise the week's topics (incl. maths), timed PYQ test, error log | F38: Maths revision inside the test | G38: 30 | H38: 0 | I38: 90 | J38: 60 | K38: =(G38+H38+I38+J38)/60 -> 3
A39: 46342 | B39: =TEXT(A39,"ddd") -> Mon | C39: GATE + Uni learning | D39: Compiler Design | E39: Day 3: Parsing II: bottom-up, LR(0) & SLR(1) | F39: M30: Probability basics | G39: 20 | H39: 40 | I39: 75 | J39: 45 | K39: =(G39+H39+I39+J39)/60 -> 3
A40: 46343 | B40: =TEXT(A40,"ddd") -> Tue | C40: GATE + Uni learning | D40: Compiler Design | E40: Day 4: Parsing III: CLR(1), LALR(1), operator precedence | F40: M31: Conditional probability & independence | G40: 20 | H40: 40 | I40: 75 | J40: 45 | K40: =(G40+H40+I40+J40)/60 -> 3
A41: 46344 | B41: =TEXT(A41,"ddd") -> Wed | C41: GATE + Uni learning | D41: Compiler Design | E41: Day 5: Syntax-directed translation | F41: M32: Bayes' theorem & total probability | G41: 20 | H41: 40 | I41: 75 | J41: 45 | K41: =(G41+H41+I41+J41)/60 -> 3
A42: 46345 | B42: =TEXT(A42,"ddd") -> Thu | C42: GATE + Uni learning | D42: Compiler Design | E42: Day 6: Intermediate code & runtime environments | F42: M33: Random variables: PMF, PDF, CDF | G42: 20 | H42: 40 | I42: 75 | J42: 45 | K42: =(G42+H42+I42+J42)/60 -> 3
A43: 46346 | B43: =TEXT(A43,"ddd") -> Fri | C43: GATE + Uni learning | D43: Compiler Design | E43: Day 7: Code optimisation & data-flow analysis | F43: M34: Expectation, variance & standard deviation | G43: 20 | H43: 40 | I43: 75 | J43: 45 | K43: =(G43+H43+I43+J43)/60 -> 3
... A48: 46351 | B48: =TEXT(A48,"ddd") -> Wed | C48: GATE + Uni learning | D48: Operating Systems | E48: Day 4: CPU scheduling II | F48: M38: Exponential distribution | G48: 20 | H48: 40 | I48: 75 | J48: 45 | K48: =(G48+H48+I48+J48)/60 -> 3
A49: 46352 | B49: =TEXT(A49,"ddd") -> Thu | C49: GATE + Uni learning | D49: Operating Systems | E49: Day 5: Process synchronisation I | F49: M39: Normal distribution | G49: 20 | H49: 35 | I49: 65 | J49: 30 | K49: =(G49+H49+I49+J49)/60 -> 2.5 | L49: Practical-exam window: lighter 2.5h load
A50: 46353 | B50: =TEXT(A50,"ddd") -> Fri | C50: GATE + Uni learning | D50: Operating Systems | E50: Day 6: Process synchronisation II | F50: M40: Statistics: mean, median, mode & standard deviation | G50: 20 | H50: 35 | I50: 65 | J50: 30 | K50: =(G50+H50+I50+J50)/60 -> 2.5 | L50: Practical-exam window: lighter 2.5h load
A51: 46354 | B51: =TEXT(A51,"ddd") -> Sat | C51: GATE + Uni learning | D51: Operating Systems | E51: Day 7: Deadlocks | F51: M41: Probability problem-solving: Bayes + distributions | G51: 20 | H51: 35 | I51: 65 | J51: 30 | K51: =(G51+H51+I51+J51)/60 -> 2.5 | L51: Practical-exam window: lighter 2.5h load
A52: 46355 | B52: =TEXT(A52,"ddd") -> Sun | C52: Weekly revision + test | D52: Revision | E52: Revise the week's topics (incl. maths), timed PYQ test, error log | F52: Maths revision inside the test | G52: 30 | H52: 0 | I52: 90 | J52: 60 | K52: =(G52+H52+I52+J52)/60 -> 3
A53: 46356 | B53: =TEXT(A53,"ddd") -> Mon | C53: GATE + Uni learning | D53: Operating Systems | E53: Day 8: Memory management: paging & segmentation | F53: M42: Calculus: limits | G53: 20 | H53: 35 | I53: 65 | J53: 30 | K53: =(G53+H53+I53+J53)/60 -> 2.5 | L53: Practical-exam window: lighter 2.5h load
A54: 46357 | B54: =TEXT(A54,"ddd") -> Tue | C54: GATE + Uni learning | D54: Operating Systems | E54: Day 9: Virtual memory | F54: M43: Calculus: continuity | G54: 20 | H54: 35 | I54: 65 | J54: 30 | K54: =(G54+H54+I54+J54)/60 -> 2.5 | L54: Practical-exam window: lighter 2.5h load
A55: 46358 | B55: =TEXT(A55,"ddd") -> Wed | C55: GATE + Uni learning | D55: Operating Systems | E55: Day 10: File systems, disk scheduling & I/O | F55: M44: Calculus: differentiability | G55: 20 | H55: 35 | I55: 65 | J55: 30 | K55: =(G55+H55+I55+J55)/60 -> 2.5 | L55: Practical-exam window: lighter 2.5h load
A56: 46359 | B56: =TEXT(A56,"ddd") -> Thu | C56: GATE + Uni learning | D56: Computer Networks | E56: Day 1: Layering, switching & performance metrics | F56: M45: Mean value theorems | G56: 20 | H56: 35 | I56: 65 | J56: 30 | K56: =(G56+H56+I56+J56)/60 -> 2.5 | L56: Practical-exam window: lighter 2.5h load
A57: 46360 | B57: =TEXT(A57,"ddd") -> Fri | C57: GATE + Uni learning | D57: Computer Networks | E57: Day 2: Data link I: framing & error detection | F57: M46: Maxima & minima | G57: 20 | H57: 35 | I57: 65 | J57: 30 | K57: =(G57+H57+I57+J57)/60 -> 2.5 | L57: Practical-exam window: lighter 2.5h load
A58: 46361 | B58: =TEXT(A58,"ddd") -> Sat | C58: GATE + Uni learning | D58: Computer Networks | E58: Day 3: Data link II: flow control & ARQ | F58: M47: Integration I | G58: 20 | H58: 35 | I58: 65 | J58: 30 | K58: =(G58+H58+I58+J58)/60 -> 2.5 | L58: Practical-exam window: lighter 2.5h load
A59: 46362 | B59: =TEXT(A59,"ddd") -> Sun | C59: Weekly revision + test | D59: Revision | E59: Weekly revision + SE starter (IPU syllabus & PYQs) | F59: Maths revision inside the test | G59: 30 | H59: 0 | I59: 90 | J59: 60 | K59: =(G59+H59+I59+J59)/60 -> 3
A60: 46363 | B60: =TEXT(A60,"ddd") -> Mon | C60: GATE + Uni learning | D60: Computer Networks | E60: Day 4: MAC & Ethernet | F60: M48: Integration II | G60: 20 | H60: 40 | I60: 75 | J60: 45 | K60: =(G60+H60+I60+J60)/60 -> 3
A61: 46364 | B61: =TEXT(A61,"ddd") -> Tue | C61: GATE + Uni learning | D61: Computer Networks | E61: Day 5: Network layer I: IPv4, subnetting, CIDR, NAT | F61: M49: Integration III & calculus revision | G61: 20 | H61: 40 | I61: 75 | J61: 45 | K61: =(G61+H61+I61+J61)/60 -> 3
A62: 46365 | B62: =TEXT(A62,"ddd") -> Wed | C62: GATE + Uni learning | D62: Computer Networks | E62: Day 6: Network layer II: routing | F62: M50: Calculus problem-solving with PYQs | G62: 20 | H62: 40 | I62: 75 | J62: 45 | K62: =(G62+H62+I62+J62)/60 -> 3
A63: 46366 | B63: =TEXT(A63,"ddd") -> Thu | C63: GATE + Uni learning | D63: Computer Networks | E63: Day 7: Transport layer: UDP, TCP & sockets | F63: M51: Discrete Maths consolidation (PYQs) | G63: 20 | H63: 40 | I63: 75 | J63: 45 | K63: =(G63+H63+I63+J63)/60 -> 3
A64: 46367 | B64: =TEXT(A64,"ddd") -> Fri | C64: Uni revision | D64: DAA | E64: DAA revision I: recurrences, sorting, D&C, hashing | G64: 30 | H64: 0 | I64: 100 | J64: 50 | K64: =(G64+H64+I64+J64)/60 -> 3
A65: 46368 | B65: =TEXT(A65,"ddd") -> Sat | C65: Uni revision | D65: DAA | E65: DAA revision II: greedy, DP, graph algorithms, NP/backtracking | G65: 30 | H65: 0 | I65: 100 | J65: 50 | K65: =(G65+H65+I65+J65)/60 -> 3
A66: 46369 | B66: =TEXT(A66,"ddd") -> Sun | C66: Uni revision (Sunday) | D66: DAA | E66: DAA full timed mock paper | G66: 0 | H66: 0 | I66: 180 | J66: 0 | K66: =(G66+H66+I66+J66)/60 -> 3
A67: 46370 | B67: =TEXT(A67,"ddd") -> Mon | C67: Uni revision | D67: DAA + CD | E67: DAA final polish + CD skim | G67: 30 | H67: 0 | I67: 100 | J67: 50 | K67: =(G67+H67+I67+J67)/60 -> 3
A68: 46371 | B68: =TEXT(A68,"ddd") -> Tue | C68: UNI EXAM – DAA (2-5 PM) | D68: DAA | E68: EXAM DAY: CIC-311 Design & Analysis of Algorithms | G68: 0 | H68: 0 | I68: 60 | J68: 0 | K68: =(G68+H68+I68+J68)/60 -> 1 | L68: Exam is 2-5 PM; only light revision in the morning
A69: 46372 | B69: =TEXT(A69,"ddd") -> Wed | C69: Uni revision | D69: CD | E69: CD full revision day | G69: 30 | H69: 0 | I69: 100 | J69: 50 | K69: =(G69+H69+I69+J69)/60 -> 3
A70: 46373 | B70: =TEXT(A70,"ddd") -> Thu | C70: UNI EXAM – CD (2-5 PM) | D70: CD | E70: EXAM DAY: CIC-303 Compiler Design | G70: 0 | H70: 0 | I70: 60 | J70: 0 | K70: =(G70+H70+I70+J70)/60 -> 1 | L70: Exam is 2-5 PM; only light revision in the morning
A71: 46374 | B71: =TEXT(A71,"ddd") -> Fri | C71: Uni revision | D71: OS | E71: OS full revision day | G71: 30 | H71: 0 | I71: 100 | J71: 50 | K71: =(G71+H71+I71+J71)/60 -> 3
A72: 46375 | B72: =TEXT(A72,"ddd") -> Sat | C72: UNI EXAM – OS (2-5 PM) | D72: OS | E72: EXAM DAY: CIC-305 Operating Systems | G72: 0 | H72: 0 | I72: 60 | J72: 0 | K72: =(G72+H72+I72+J72)/60 -> 1 | L72: Exam is 2-5 PM; only light revision in the morning
A73: 46376 | B73: =TEXT(A73,"ddd") -> Sun | C73: Uni revision (Sunday) | D73: CN | E73: CN revision I: numericals | G73: 0 | H73: 0 | I73: 180 | J73: 0 | K73: =(G73+H73+I73+J73)/60 -> 3
A74: 46377 | B74: =TEXT(A74,"ddd") -> Mon | C74: Uni revision | D74: CN | E74: CN Day 8: Application layer (DNS, HTTP & email) first, then CN revision II: theory + IPU paper | G74: 0 | H74: 0 | I74: 130 | J74: 50 | K74: =(G74+H74+I74+J74)/60 -> 3 | L74: Moved here from the original plan (late start). Only new topic = CN Day 8 – finish it first, then revise theory.
A75: 46378 | B75: =TEXT(A75,"ddd") -> Tue | C75: UNI EXAM – CN (2-5 PM) | D75: CN | E75: EXAM DAY: CIC-307 Computer Networks | G75: 0 | H75: 0 | I75: 60 | J75: 0 | K75: =(G75+H75+I75+J75)/60 -> 1 | L75: Exam is 2-5 PM; only light revision in the morning
A76: 46379 | B76: =TEXT(A76,"ddd") -> Wed | C76: Uni revision | D76: Software Engg | E76: Software Engineering (CIC-309) full day | G76: 30 | H76: 0 | I76: 120 | J76: 30 | K76: =(G76+H76+I76+J76)/60 -> 3
A77: 46380 | B77: =TEXT(A77,"ddd") -> Thu | C77: UNI EXAM – SE (2-5 PM) | D77: Software Engg | E77: EXAM DAY: CIC-309 Software Engineering | G77: 0 | H77: 0 | I77: 60 | J77: 0 | K77: =(G77+H77+I77+J77)/60 -> 1 | L77: Exam is 2-5 PM; only light revision in the morning
A78: 46381 | B78: =TEXT(A78,"ddd") -> Fri | C78: Uni revision | D78: Economics | E78: Economics for Engineering (HS-301) – day 1 | G78: 30 | H78: 0 | I78: 120 | J78: 30 | K78: =(G78+H78+I78+J78)/60 -> 3
A79: 46382 | B79: =TEXT(A79,"ddd") -> Sat | C79: Uni revision | D79: Economics | E79: Economics for Engineering – day 2 | G79: 30 | H79: 0 | I79: 120 | J79: 30 | K79: =(G79+H79+I79+J79)/60 -> 3
A80: 46383 | B80: =TEXT(A80,"ddd") -> Sun | C80: Uni revision (Sunday) | D80: Economics | E80: Economics – full paper + final revision | G80: 0 | H80: 0 | I80: 180 | J80: 0 | K80: =(G80+H80+I80+J80)/60 -> 3
A81: 46384 | B81: =TEXT(A81,"ddd") -> Mon | C81: UNI EXAM – Economics (2-5 PM) | D81: Economics | E81: EXAM DAY: HS-301 Economics for Engineering | G81: 0 | H81: 0 | I81: 60 | J81: 0 | K81: =(G81+H81+I81+J81)/60 -> 1 | L81: Exam is 2-5 PM; only light revision in the morning
A82: 46385 | B82: =TEXT(A82,"ddd") -> Tue | C82: GATE consolidation | D82: OS + CN + Discrete | E82: GATE recap I: OS + CN + Discrete Maths | F82: M52: LA + Probability + Calculus consolidation (PYQs) + maths revision | G82: 20 | H82: 40 | I82: 70 | J82: 50 | K82: =(G82+H82+I82+J82)/60 -> 3 | L82: Also today: Maths M52 (sheet 7) and Aptitude Day 52 (sheet 8), moved here from the original plan.
A83: 46386 | B83: =TEXT(A83,"ddd") -> Wed | C83: GATE consolidation | D83: Algo/DS/C/CD + LA/Prob/Calc | E83: GATE recap II: Algorithms, DS, C, CD + LA/Prob/Calc | F83: Maths revision (PYQs) | G83: 20 | H83: 40 | I83: 70 | J83: 50 | K83: =(G83+H83+I83+J83)/60 -> 3
A84: 46387 | B84: =TEXT(A84,"ddd") -> Thu | C84: GATE consolidation | D84: All 6 covered sections | E84: Sectional mock + January plan | G84: 0 | H84: 0 | I84: 160 | J84: 20 | K84: =(G84+H84+I84+J84)/60 -> 3
E85: Total hours | K85: =SUM(K5:K84) -> 213.5
E86: Average hours per day | K86: =AVERAGE(K5:K84) -> 2.66875
E87: Legend: orange = university exam day, green = Sunday revision

Sheet 1 C Programming
A1: C Programming – day-by-day plan
A2: GATE (foundation) | The STATUS column here tracks only THIS subject. Maths is tracked in sheet 7, Aptitude in sheet 8.
A4: Playlists & teachers
A5: Main playlist | D5: C Programming | GATE 2024 | Vishvadeep Gothi Sir · Vishvadeep Gothi Sir [40 videos]
A6: Revision / PYQ playlist | D6: Introduction to Programming in C - Satyadev Nandakumar | IIT Kanpur: NPTEL · Satyadev Nandakumar (IIT Kanpur) [55 videos]
A7: Topic-wise PYQs | D7: GATE Overflow GO-PDFs (2025) → open 'Programming in C'
A8: Textbook | D8: K&R – The C Programming Language (2E), ch 1-8
A9: Free tests | D9: GO2017 Programming 1 | E9: GO Programming Test 2 | F9: Programming GATE2020 PG-1 | G9: Programming GATE2020 PG-2
A11: Day # | B11: Date | C11: Day | D11: Aptitude today (reference – track in sheet 8) | E11: MATHS lecture today (reference – track in sheet 7) | F11: Maths playlist · teacher (click) | G11: Maths video search ▶ | H11: MAIN lecture topic | I11: What's covered | J11: Main playlist · teacher (click) | K11: Main video search ▶ | L11: Also use today: PYQ / extra playlist · teacher (click) | M11: Textbook | N11: Practice (PYQs) | O11: Planned hrs (whole day) | P11: STATUS – this subject only | Q11: Notes
A12: 1 | B12: 46308 | C12: =TEXT(B12,"ddd") -> Tue | D12: Aptitude: Percentages & ratios – 8-10 easy Qs (15 min). Source: Complete Course on General Aptitude for GATE & ESE 2025 & 2026 (Unacademy) | E12: Day 1: Propositional logic I: propositions, connectives, truth tables | F12: Propositional Logic - Complete Summary, All GATE PYQs & Practice Questions | Discrete Mathematics · GO Classes for GATE CS (instructor not named in playlist) | G12: Search this lecture ▶ | H12: Basics: data types, operators, precedence | I12: C program structure, data types & sizes, variables, all operators (incl. bitwise, ++/-- tricks), precedence/associativity, implicit & explicit type conversion. | J12: C Programming | GATE 2024 | Vishvadeep Gothi Sir · Vishvadeep Gothi Sir | K12: Search this lecture ▶ | L12: Introduction to Programming in C - Satyadev Nandakumar | IIT Kanpur: NPTEL · Satyadev Nandakumar (IIT Kanpur) | M12: K&R ch 1-2 | N12: GO-PDFs → Programming in C → Operators & expressions / data types – 10 Qs (output tracing) | O12: 2 | P12: Not Started
A13: 2 | B13: 46309 | C13: =TEXT(B13,"ddd") -> Wed | D13: Aptitude: Time & work – 8-10 easy Qs (15 min). Source: Complete Course on General Aptitude for GATE & ESE 2025 & 2026 (Unacademy) | E13: Day 2: Propositional logic II: equivalences, tautology, normal forms | F13: Propositional Logic - Complete Summary, All GATE PYQs & Practice Questions | Discrete Mathematics · GO Classes for GATE CS (instructor not named in playlist) | G13: Search this lecture ▶ | H13: Control flow & I/O | I13: if/else, switch, loops, break/continue, printf/scanf format specifiers, tricky output questions. | J13: C Programming | GATE 2024 | Vishvadeep Gothi Sir · Vishvadeep Gothi Sir | K13: Search this lecture ▶ | L13: Introduction to Programming in C - Satyadev Nandakumar | IIT Kanpur: NPTEL · Satyadev Nandakumar (IIT Kanpur) | M13: K&R ch 3, 7.2-7.3 | N13: GO-PDFs → Programming in C → Loops & control flow output questions – 10 Qs | O13: 2 | P13: Not Started
A14: 3 | B14: 46310 | C14: =TEXT(B14,"ddd") -> Thu | D14: Aptitude: Speed, time & distance – 8-10 easy Qs (15 min). Source: Complete Course on General Aptitude for GATE & ESE 2025 & 2026 (Unacademy) | E14: Day 3: Propositional logic III: inference, validity, functional completeness | F14: Propositional Logic - Complete Summary, All GATE PYQs & Practice Questions | Discrete Mathematics · GO Classes for GATE CS (instructor not named in playlist) | G14: Search this lecture ▶ | H14: Functions, recursion & storage classes | I14: Function call/return, call by value, recursion (trace stack frames), scope, auto/static/extern/register. | J14: C Programming | GATE 2024 | Vishvadeep Gothi Sir · Vishvadeep Gothi Sir | K14: Search this lecture ▶ | L14: Introduction to Programming in C - Satyadev Nandakumar | IIT Kanpur: NPTEL · Satyadev Nandakumar (IIT Kanpur) | M14: K&R ch 4 | N14: GO-PDFs → Programming in C → Recursion & storage-class PYQs – 12 Qs | O14: 2 | P14: Not Started
A15: 4 | B15: 46311 | C15: =TEXT(B15,"ddd") -> Fri | D15: Aptitude: Profit/loss & averages – 8-10 easy Qs (15 min). Source: Complete Course on General Aptitude for GATE & ESE 2025 & 2026 (Unacademy) | E15: Day 4: First-order logic I: predicates & quantifiers | F15: Propositional Logic - Complete Summary, All GATE PYQs & Practice Questions | Discrete Mathematics · GO Classes for GATE CS (instructor not named in playlist) | G15: Search this lecture ▶ | H15: Arrays, strings & pointer basics | I15: 1-D/2-D arrays, row-major address calculation, strings & string.h functions, pointer declaration, pointer arithmetic. | J15: C Programming | GATE 2024 | Vishvadeep Gothi Sir · Vishvadeep Gothi Sir | K15: Search this lecture ▶ | L15: Introduction to Programming in C - Satyadev Nandakumar | IIT Kanpur: NPTEL · Satyadev Nandakumar (IIT Kanpur) | M15: K&R ch 5.1-5.5 | N15: GO-PDFs → Programming in C → Arrays & pointers PYQs – 12 Qs | O15: 2 | P15: Not Started | Q15: If FOL isn't inside this playlist, search 'GO Classes first order logic' (not in your resource PDF).
A16: 5 | B16: 46312 | C16: =TEXT(B16,"ddd") -> Sat | D16: Aptitude: Number series & sequences – 8-10 easy Qs (15 min). Source: Complete Course on General Aptitude for GATE & ESE 2025 & 2026 (Unacademy) | E16: Day 5: First-order logic II: translation & nested quantifiers | F16: Propositional Logic - Complete Summary, All GATE PYQs & Practice Questions | Discrete Mathematics · GO Classes for GATE CS (instructor not named in playlist) | G16: Search this lecture ▶ | H16: Advanced pointers, structs, unions, malloc, macros | I16: Pointer-to-pointer, array of pointers, function pointers, struct/union sizes & padding, malloc/calloc/free, #define macros pitfalls. | J16: C Programming | GATE 2024 | Vishvadeep Gothi Sir · Vishvadeep Gothi Sir | K16: Search this lecture ▶ | L16: Introduction to Programming in C - Satyadev Nandakumar | IIT Kanpur: NPTEL · Satyadev Nandakumar (IIT Kanpur) | M16: K&R ch 5.6-5.12, 6 | N16: GO-PDFs → Programming in C → Pointers/structs PYQs – 15 Qs + full C topic recap | O16: 2 | P16: Not Started | Q16: Same note as day 4.
N17: Total planned hours | O17: =SUM(O12:O16) -> 10

Sheet 2 Data Structures
A1: Data Structures – day-by-day plan
A2: GATE (foundation) | The STATUS column here tracks only THIS subject. Maths is tracked in sheet 7, Aptitude in sheet 8.
A4: Playlists & teachers
A5: Main playlist | D5: Data Structures By Vishwadeep · Vishwadeep Sir [40 videos]
A6: Revision / PYQ playlist | D6: Data Structure: GATE PYQs | GATE/ESE 2022 | Vishvadeep Sir · Vishvadeep Sir (Unacademy Computer Science) [23 videos]
A7: More | D7: Computer Sc - Data Structures and Algorithms (NPTEL) · Dr. Naveen Garg, IIT Delhi [36 videos]
A8: Topic-wise PYQs | D8: GATE Overflow GO-PDFs (2025) → open 'Data Structures'
A9: Textbook | D9: Karumanchi – Data Structures & Algorithms Made Easy (chapter names given per day)
A10: Free tests | D10: Data Structure Set 2 | E10: DS GATE2020 PG-1 | F10: DS GATE2020 PG-2 | G10: DS GATE2020 PG-3 | H10: DS GATE2020 PG-4
A12: Day # | B12: Date | C12: Day | D12: Aptitude today (reference – track in sheet 8) | E12: MATHS lecture today (reference – track in sheet 7) | F12: Maths playlist · teacher (click) | G12: Maths video search ▶ | H12: MAIN lecture topic | I12: What's covered | J12: Main playlist · teacher (click) | K12: Main video search ▶ | L12: Also use today: PYQ / extra playlist · teacher (click) | M12: Textbook | N12: Practice (PYQs) | O12: Planned hrs (whole day) | P12: STATUS – this subject only | Q12: Notes
A13: 1 | B13: 46314 | C13: =TEXT(B13,"ddd") -> Mon | D13: Aptitude: Basic counting & probability (aptitude level) – 8-10 easy Qs (20 min). Source: Complete Course on General Aptitude for GATE & ESE 2025 & 2026 (Unacademy) | E13: Day 6: Sets: operations, power set, cardinality | F13: Set Theory - GATE PYQs, Summary, Practice, Revision | Discrete Mathematics · GO Classes for GATE CS (instructor not named in playlist) | G13: Search this lecture ▶ | H13: Arrays & singly linked list | I13: Array operations & complexity, singly linked list: insert/delete/search/reverse, find middle, detect loop. | J13: Data Structures By Vishwadeep · Vishwadeep Sir | K13: Search this lecture ▶ | L13: Data Structure: GATE PYQs | GATE/ESE 2022 | Vishvadeep Sir · Vishvadeep Sir (Unacademy Computer Science) | M13: Karumanchi: Linked Lists | N13: GO-PDFs → Data Structures → Linked list PYQs – 10 Qs | O13: 2.5 | P13: Not Started
A14: 2 | B14: 46315 | C14: =TEXT(B14,"ddd") -> Tue | D14: Aptitude: Data interpretation (tables, bar charts) – 8-10 easy Qs (20 min). Source: Complete Course on General Aptitude for GATE & ESE 2025 & 2026 (Unacademy) | E14: Day 7: Relations I: types & representation | F14: Set Theory - GATE PYQs, Summary, Practice, Revision | Discrete Mathematics · GO Classes for GATE CS (instructor not named in playlist) | G14: Search this lecture ▶ | H14: Doubly/circular linked list & stacks | I14: Doubly & circular LL, stack (array & LL), push/pop, stack applications. | J14: Data Structures By Vishwadeep · Vishwadeep Sir | K14: Search this lecture ▶ | L14: Data Structure: GATE PYQs | GATE/ESE 2022 | Vishvadeep Sir · Vishvadeep Sir (Unacademy Computer Science) | M14: Karumanchi: Linked Lists, Stacks | N14: GO-PDFs → Data Structures → Stack & LL PYQs – 10 Qs | O14: 2.5 | P14: Not Started | Q14: Closest playlist from your PDF; if relations aren't covered, search 'GO Classes relations discrete mathematics'.
A15: 3 | B15: 46316 | C15: =TEXT(B15,"ddd") -> Wed | D15: Aptitude: Verbal: tenses & subject-verb agreement – 8-10 easy Qs (20 min). Source: GATE Overflow – verbal aptitude lessons | E15: Day 8: Relations II: equivalence relations, partitions, closures | F15: Set Theory - GATE PYQs, Summary, Practice, Revision | Discrete Mathematics · GO Classes for GATE CS (instructor not named in playlist) | G15: Search this lecture ▶ | H15: Expression conversion, queues & deque | I15: Infix/postfix/prefix conversion & evaluation, queue, circular queue, deque, stack using queues & queue using stacks. | J15: Data Structures By Vishwadeep · Vishwadeep Sir | K15: Search this lecture ▶ | L15: Data Structure: GATE PYQs | GATE/ESE 2022 | Vishvadeep Sir · Vishvadeep Sir (Unacademy Computer Science) | M15: Karumanchi: Stacks, Queues | N15: GO-PDFs → Data Structures → Stack/Queue PYQs – 12 Qs | O15: 2.5 | P15: Not Started | Q15: Same note as day 7.
A16: 4 | B16: 46317 | C16: =TEXT(B16,"ddd") -> Thu | D16: Aptitude: Verbal: sentence completion & prepositions – 8-10 easy Qs (20 min). Source: GATE Overflow – verbal aptitude lessons | E16: Day 9: Functions: injective, surjective, bijective | F16: Set Theory - GATE PYQs, Summary, Practice, Revision | Discrete Mathematics · GO Classes for GATE CS (instructor not named in playlist) | G16: Search this lecture ▶ | H16: Binary trees & traversals | I16: Tree terminology, binary tree properties (nodes/height), in/pre/post/level-order, construct tree from two traversals, number of trees (Catalan). | J16: Data Structures By Vishwadeep · Vishwadeep Sir | K16: Search this lecture ▶ | L16: Data Structure: GATE PYQs | GATE/ESE 2022 | Vishvadeep Sir · Vishvadeep Sir (Unacademy Computer Science) | M16: Karumanchi: Trees | N16: GO-PDFs → Data Structures → Binary tree PYQs – 12 Qs | O16: 2.5 | P16: Not Started | Q16: Same note as day 7.
A17: 5 | B17: 46318 | C17: =TEXT(B17,"ddd") -> Fri | D17: Aptitude: Verbal: synonyms, antonyms & idioms – 8-10 easy Qs (20 min). Source: GATE Overflow – verbal aptitude lessons | E17: Day 10: Partial orders & Hasse diagrams | F17: Set Theory - GATE PYQs, Summary, Practice, Revision | Discrete Mathematics · GO Classes for GATE CS (instructor not named in playlist) | G17: Search this lecture ▶ | H17: BST & AVL trees | I17: BST insert/delete/search, inorder = sorted, height-balanced AVL trees & rotations, min/max nodes in AVL. | J17: Data Structures By Vishwadeep · Vishwadeep Sir | K17: Search this lecture ▶ | L17: Data Structure: GATE PYQs | GATE/ESE 2022 | Vishvadeep Sir · Vishvadeep Sir (Unacademy Computer Science) | M17: Karumanchi: Trees (BST, AVL) | N17: GO-PDFs → Data Structures → BST/AVL PYQs – 12 Qs | O17: 2.5 | P17: Not Started | Q17: Same note as day 7.
A18: 6 | B18: 46319 | C18: =TEXT(B18,"ddd") -> Sat | D18: Aptitude: Reading comprehension (1 passage) – 8-10 easy Qs (20 min). Source: GATE Overflow – verbal aptitude lessons | E18: Day 11: Lattices | F18: Set Theory - GATE PYQs, Summary, Practice, Revision | Discrete Mathematics · GO Classes for GATE CS (instructor not named in playlist) | G18: Search this lecture ▶ | H18: Binary heaps & priority queue | I18: Heap property, insert/delete-min, heapify, build-heap O(n), heap sort idea, priority queue. | J18: Data Structures By Vishwadeep · Vishwadeep Sir | K18: Search this lecture ▶ | L18: Data Structure: GATE PYQs | GATE/ESE 2022 | Vishvadeep Sir · Vishvadeep Sir (Unacademy Computer Science) | M18: Karumanchi: Priority Queues & Heaps | N18: GO-PDFs → Data Structures → Heap PYQs – 10 Qs | O18: 2.5 | P18: Not Started | Q18: Same note as day 7.
A19: 7 | B19: 46321 | C19: =TEXT(B19,"ddd") -> Mon | D19: Aptitude: Para-jumbles & sentence ordering – 8-10 easy Qs (20 min). Source: GATE Overflow – verbal aptitude lessons | E19: Day 12: Monoids, semigroups & groups | F19: Group Theory Complete Course - Abstract Algebra Course | Discrete Mathematics | Monoid, Groupoid, Semigroup, Abelian Group, Cyclic Group, Subgroup · GO Classes for GATE CS (instructor not named in playlist) | G19: Search this lecture ▶ | H19: Graph representation & basic traversals | I19: Directed/undirected graphs, adjacency matrix vs list, degree, paths/cycles, BFS/DFS first look (full treatment in Algorithms). | J19: Data Structures By Vishwadeep · Vishwadeep Sir | K19: Search this lecture ▶ | L19: Data Structure: GATE PYQs | GATE/ESE 2022 | Vishvadeep Sir · Vishvadeep Sir (Unacademy Computer Science) | M19: Karumanchi: Graph Algorithms (intro) | N19: GO-PDFs → Data Structures → Graph basics PYQs – 10 Qs | O19: 3 | P19: Not Started
A20: 8 | B20: 46322 | C20: =TEXT(B20,"ddd") -> Tue | D20: Aptitude: Logical reasoning: arrangements & puzzles – 8-10 easy Qs (20 min). Source: Complete Course on General Aptitude for GATE & ESE 2025 & 2026 (Unacademy) | E20: Day 13: Subgroups, cyclic groups & Lagrange's theorem | F20: Group Theory Complete Course - Abstract Algebra Course | Discrete Mathematics | Monoid, Groupoid, Semigroup, Abelian Group, Cyclic Group, Subgroup · GO Classes for GATE CS (instructor not named in playlist) | G20: Search this lecture ▶ | H20: DS output-tracing & complexity PYQs | I20: Mixed code-tracing on LL/stack/queue/tree; time complexity of operations (table of all structures). | J20: Data Structures By Vishwadeep · Vishwadeep Sir | K20: Search this lecture ▶ | L20: Data Structure: GATE PYQs | GATE/ESE 2022 | Vishvadeep Sir · Vishvadeep Sir (Unacademy Computer Science) | M20: — | N20: GO-PDFs → Data Structures → Mixed DS PYQs – 20 Qs; build a complexity cheat-table | O20: 3 | P20: Not Started
A21: 9 | B21: 46323 | C21: =TEXT(B21,"ddd") -> Wed | D21: Aptitude: Spatial reasoning: paper folding, cubes, patterns – 8-10 easy Qs (20 min). Source: Complete Course on General Aptitude for GATE & ESE 2025 & 2026 (Unacademy) | E21: Day 14: Graph basics: degrees, handshake, special graphs | F21: Graph Theory Complete Course - Discrete Mathematics | Complete Graph Theory Course | GO Classes · GO Classes for GATE CS (instructor not named in playlist) | G21: Search this lecture ▶ | H21: DS full-topic test | I21: Timed mini-test over entire DS, then fix errors with video solutions. | J21: Data Structures By Vishwadeep · Vishwadeep Sir | K21: Search this lecture ▶ | L21: Data Structure: GATE PYQs | GATE/ESE 2022 | Vishvadeep Sir · Vishvadeep Sir (Unacademy Computer Science) | M21: — | N21: GO-PDFs → Data Structures → Attempt 'Data Structure Set 2' or a GATE2020 DS test (timed 45 min) | O21: 3 | P21: Not Started
N22: Total planned hours | O22: =SUM(O13:O21) -> 24

Sheet 3 Algorithms DAA
A1: Algorithms (DAA) – day-by-day plan
A2: GATE + Uni (CIC-311 DAA, 15 Dec) | The STATUS column here tracks only THIS subject. Maths is tracked in sheet 7, Aptitude in sheet 8.
A4: Playlists & teachers
A5: Main playlist | D5: DSA - Abdul Bari · Abdul Bari [163 videos]
A6: Revision / PYQ playlist | D6: Algorithms - Revision, GATE PYQs Complete Analysis | GO Classes | Sachin Mittal · Sachin Mittal (GO Classes) [18 videos]
A7: More | D7: Computer Sc - Design & Analysis of Algorithms (NPTEL) · Prof. Abhiram Ranade, IIT Bombay [34 videos]
A8: Topic-wise PYQs | D8: GATE Overflow GO-PDFs (2025) → open 'Algorithms'
A9: Textbook | D9: CLRS (3E) – chapters given per day; Kleinberg-Tardos ch 1-6 optional
A10: Free tests | D10: GO2017 Algorithms 1 | E10: Algorithm Test 2 | F10: Algorithms Previous GATE 1 | G10: Algorithms GATE2020 PG-1 | H10: Algorithms GATE2020 PG-2
A12: Day # | B12: Date | C12: Day | D12: Aptitude today (reference – track in sheet 8) | E12: MATHS lecture today (reference – track in sheet 7) | F12: Maths playlist · teacher (click) | G12: Maths video search ▶ | H12: MAIN lecture topic | I12: What's covered | J12: Main playlist · teacher (click) | K12: Main video search ▶ | L12: Also use today: PYQ / extra playlist · teacher (click) | M12: Textbook | N12: Practice (PYQs) | O12: Planned hrs (whole day) | P12: STATUS – this subject only | Q12: Notes
A13: 1 | B13: 46324 | C13: =TEXT(B13,"ddd") -> Thu | D13: Aptitude: Percentages & ratios – 8-10 easy Qs (20 min). Source: Complete Course on General Aptitude for GATE & ESE 2025 & 2026 (Unacademy) | E13: Day 15: Connectivity | F13: Graph Theory Complete Course - Discrete Mathematics | Complete Graph Theory Course | GO Classes · GO Classes for GATE CS (instructor not named in playlist) | G13: Search this lecture ▶ | H13: Asymptotic notation & complexity analysis | I13: Big-O/Omega/Theta, growth-rate ordering, time & space complexity, analysing loops and nested loops. | J13: DSA - Abdul Bari · Abdul Bari | K13: Search this lecture ▶ | L13: Algorithms - Revision, GATE PYQs Complete Analysis | GO Classes | Sachin Mittal · Sachin Mittal (GO Classes) | M13: CLRS ch 1, 2, 3 | N13: GO-PDFs → Algorithms → Asymptotic analysis PYQs – 12 Qs | O13: 3 | P13: Not Started
A14: 2 | B14: 46325 | C14: =TEXT(B14,"ddd") -> Fri | D14: Aptitude: Time & work – 8-10 easy Qs (20 min). Source: Complete Course on General Aptitude for GATE & ESE 2025 & 2026 (Unacademy) | E14: Day 16: Trees, Euler & Hamiltonian graphs | F14: Graph Theory Complete Course - Discrete Mathematics | Complete Graph Theory Course | GO Classes · GO Classes for GATE CS (instructor not named in playlist) | G14: Search this lecture ▶ | H14: Recurrence relations | I14: Substitution, recursion tree, Master theorem (all 3 cases + gaps), recurrences of recursive algorithms. | J14: DSA - Abdul Bari · Abdul Bari | K14: Search this lecture ▶ | L14: Algorithms - Revision, GATE PYQs Complete Analysis | GO Classes | Sachin Mittal · Sachin Mittal (GO Classes) | M14: CLRS ch 4 | N14: GO-PDFs → Algorithms → Recurrence PYQs – 12 Qs | O14: 3 | P14: Not Started
A15: 3 | B15: 46326 | C15: =TEXT(B15,"ddd") -> Sat | D15: Aptitude: Speed, time & distance – 8-10 easy Qs (20 min). Source: Complete Course on General Aptitude for GATE & ESE 2025 & 2026 (Unacademy) | E15: Day 17: Planar graphs & matching | F15: Graph Theory Complete Course - Discrete Mathematics | Complete Graph Theory Course | GO Classes · GO Classes for GATE CS (instructor not named in playlist) | G15: Search this lecture ▶ | H15: Searching & basic sorting | I15: Linear/binary search, bubble, selection, insertion sort; stability, in-place, best/worst cases, inversions. | J15: DSA - Abdul Bari · Abdul Bari | K15: Search this lecture ▶ | L15: Algorithms - Revision, GATE PYQs Complete Analysis | GO Classes | Sachin Mittal · Sachin Mittal (GO Classes) | M15: CLRS ch 2 | N15: GO-PDFs → Algorithms → Sorting PYQs (basic) – 10 Qs | O15: 3 | P15: Not Started
A16: 4 | B16: 46328 | C16: =TEXT(B16,"ddd") -> Mon | D16: Aptitude: Profit/loss & averages – 8-10 easy Qs (20 min). Source: Complete Course on General Aptitude for GATE & ESE 2025 & 2026 (Unacademy) | E16: Day 18: Graph colouring | F16: Graph Theory Complete Course - Discrete Mathematics | Complete Graph Theory Course | GO Classes · GO Classes for GATE CS (instructor not named in playlist) | G16: Search this lecture ▶ | H16: Merge, quick, heap sort & lower bounds | I16: Merge sort, quick sort (partition, worst case, randomized), heap sort, counting/radix/bucket sort, Omega(n log n) bound. | J16: DSA - Abdul Bari · Abdul Bari | K16: Search this lecture ▶ | L16: Algorithms - Revision, GATE PYQs Complete Analysis | GO Classes | Sachin Mittal · Sachin Mittal (GO Classes) | M16: CLRS ch 6, 7, 8 | N16: GO-PDFs → Algorithms → Sorting PYQs (advanced) – 15 Qs | O16: 3 | P16: Not Started
A17: 5 | B17: 46329 | C17: =TEXT(B17,"ddd") -> Tue | D17: Aptitude: Number series & sequences – 8-10 easy Qs (20 min). Source: Complete Course on General Aptitude for GATE & ESE 2025 & 2026 (Unacademy) | E17: Day 19: Counting I: rules, permutations & combinations | F17: Combinatorics Complete Course | Discrete Mathematics | Basic Counting Principles, Permutation & Combination | Generating Function, Recurrence Relation · GO Classes for GATE CS (instructor not named in playlist) | G17: Search this lecture ▶ | H17: Hashing | I17: Hash functions, chaining, open addressing (linear, quadratic, double), load factor, expected probes, insertion order questions. | J17: DSA - Abdul Bari · Abdul Bari | K17: Search this lecture ▶ | L17: Algorithms - Revision, GATE PYQs Complete Analysis | GO Classes | Sachin Mittal · Sachin Mittal (GO Classes) | M17: CLRS ch 11.1-11.4 | N17: GO-PDFs → Algorithms → Hashing PYQs – 12 Qs | O17: 3 | P17: Not Started
A18: 6 | B18: 46330 | C18: =TEXT(B18,"ddd") -> Wed | D18: Aptitude: Basic counting & probability (aptitude level) – 8-10 easy Qs (20 min). Source: Complete Course on General Aptitude for GATE & ESE 2025 & 2026 (Unacademy) | E18: Day 20: Counting II: pigeonhole, inclusion-exclusion, stars & bars | F18: Combinatorics Complete Course | Discrete Mathematics | Basic Counting Principles, Permutation & Combination | Generating Function, Recurrence Relation · GO Classes for GATE CS (instructor not named in playlist) | G18: Search this lecture ▶ | H18: Divide & conquer applications | I18: D&C paradigm, min-max finding, Strassen matrix multiplication, closest pair, comparison of D&C recurrences. | J18: DSA - Abdul Bari · Abdul Bari | K18: Search this lecture ▶ | L18: Algorithms - Revision, GATE PYQs Complete Analysis | GO Classes | Sachin Mittal · Sachin Mittal (GO Classes) | M18: CLRS ch 4.2, 9 | N18: GO-PDFs → Algorithms → D&C PYQs – 10 Qs | O18: 3 | P18: Not Started
A19: 7 | B19: 46331 | C19: =TEXT(B19,"ddd") -> Thu | D19: Aptitude: Data interpretation (tables, bar charts) – 8-10 easy Qs (20 min). Source: Complete Course on General Aptitude for GATE & ESE 2025 & 2026 (Unacademy) | E19: Day 21: Recurrence relations | F19: Recurrence Relations in Discrete Mathematics | Complete Playlist | Applications of Recurrence Relations | GO Classes · GO Classes for GATE CS (instructor not named in playlist) | G19: Search this lecture ▶ | H19: Greedy algorithms | I19: Greedy choice property, fractional knapsack, activity selection, job sequencing with deadlines, Huffman coding. | J19: DSA - Abdul Bari · Abdul Bari | K19: Search this lecture ▶ | L19: Algorithms - Revision, GATE PYQs Complete Analysis | GO Classes | Sachin Mittal · Sachin Mittal (GO Classes) | M19: CLRS ch 16.1-16.3 | N19: GO-PDFs → Algorithms → Greedy PYQs – 12 Qs | O19: 3 | P19: Not Started
A20: 8 | B20: 46332 | C20: =TEXT(B20,"ddd") -> Fri | D20: Aptitude: Verbal: tenses & subject-verb agreement – 8-10 easy Qs (20 min). Source: GATE Overflow – verbal aptitude lessons | E20: Day 22: Generating functions | F20: Combinatorics Complete Course | Discrete Mathematics | Basic Counting Principles, Permutation & Combination | Generating Function, Recurrence Relation · GO Classes for GATE CS (instructor not named in playlist) | G20: Search this lecture ▶ | H20: Graph traversals | I20: BFS, DFS, edge classification, topological sort, strongly connected components, applications. | J20: DSA - Abdul Bari · Abdul Bari | K20: Search this lecture ▶ | L20: Algorithms - Revision, GATE PYQs Complete Analysis | GO Classes | Sachin Mittal · Sachin Mittal (GO Classes) | M20: CLRS ch 22.1-22.5 | N20: GO-PDFs → Algorithms → Graph traversal PYQs – 12 Qs | O20: 3 | P20: Not Started | Q20: Generating-function videos sit near the end of this long playlist.
A21: 9 | B21: 46333 | C21: =TEXT(B21,"ddd") -> Sat | D21: Aptitude: Verbal: sentence completion & prepositions – 8-10 easy Qs (20 min). Source: GATE Overflow – verbal aptitude lessons | E21: Day 23: Matrices: types & operations | F21: Linear Algebra | GATE CSE Complete Course · GO Classes for GATE CS (instructor not named in playlist) | G21: Search this lecture ▶ | H21: Minimum spanning trees & union-find | I21: Cut property, Kruskal, Prim, union-find with path compression, number of MSTs, uniqueness conditions. | J21: DSA - Abdul Bari · Abdul Bari | K21: Search this lecture ▶ | L21: Algorithms - Revision, GATE PYQs Complete Analysis | GO Classes | Sachin Mittal · Sachin Mittal (GO Classes) | M21: CLRS ch 21, 23 | N21: GO-PDFs → Algorithms → MST PYQs – 12 Qs | O21: 3 | P21: Not Started
A22: 10 | B22: 46335 | C22: =TEXT(B22,"ddd") -> Mon | D22: Aptitude: Verbal: synonyms, antonyms & idioms – 8-10 easy Qs (20 min). Source: GATE Overflow – verbal aptitude lessons | E22: Day 24: Determinants | F22: Linear Algebra | GATE CSE Complete Course · GO Classes for GATE CS (instructor not named in playlist) | G22: Search this lecture ▶ | H22: Shortest paths | I22: Dijkstra, Bellman-Ford, Floyd-Warshall, negative edges/cycles, complexity with different data structures. | J22: DSA - Abdul Bari · Abdul Bari | K22: Search this lecture ▶ | L22: Algorithms - Revision, GATE PYQs Complete Analysis | GO Classes | Sachin Mittal · Sachin Mittal (GO Classes) | M22: CLRS ch 24, 25.2 | N22: GO-PDFs → Algorithms → Shortest-path PYQs – 12 Qs | O22: 3 | P22: Not Started
A23: 11 | B23: 46336 | C23: =TEXT(B23,"ddd") -> Tue | D23: Aptitude: Reading comprehension (1 passage) – 8-10 easy Qs (20 min). Source: GATE Overflow – verbal aptitude lessons | E23: Day 25: Rank & inverse | F23: Linear Algebra | GATE CSE Complete Course · GO Classes for GATE CS (instructor not named in playlist) | G23: Search this lecture ▶ | H23: Dynamic programming I | I23: DP idea (overlapping subproblems, optimal substructure), LCS, LIS, matrix-chain multiplication. | J23: DSA - Abdul Bari · Abdul Bari | K23: Search this lecture ▶ | L23: Algorithms - Revision, GATE PYQs Complete Analysis | GO Classes | Sachin Mittal · Sachin Mittal (GO Classes) | M23: CLRS ch 15 | N23: GO-PDFs → Algorithms → DP PYQs (part 1) – 10 Qs | O23: 3 | P23: Not Started
A24: 12 | B24: 46337 | C24: =TEXT(B24,"ddd") -> Wed | D24: Aptitude: Para-jumbles & sentence ordering – 8-10 easy Qs (20 min). Source: GATE Overflow – verbal aptitude lessons | E24: Day 26: Systems of linear equations | F24: Linear Algebra | GATE CSE Complete Course · GO Classes for GATE CS (instructor not named in playlist) | G24: Search this lecture ▶ | H24: Dynamic programming II | I24: 0/1 knapsack, coin change, edit distance, subset sum, rod cutting, DP vs greedy. | J24: DSA - Abdul Bari · Abdul Bari | K24: Search this lecture ▶ | L24: Algorithms - Revision, GATE PYQs Complete Analysis | GO Classes | Sachin Mittal · Sachin Mittal (GO Classes) | M24: CLRS ch 15 | N24: GO-PDFs → Algorithms → DP PYQs (part 2) – 12 Qs | O24: 3 | P24: Not Started
A25: 13 | B25: 46338 | C25: =TEXT(B25,"ddd") -> Thu | D25: Aptitude: Logical reasoning: arrangements & puzzles – 8-10 easy Qs (20 min). Source: Complete Course on General Aptitude for GATE & ESE 2025 & 2026 (Unacademy) | E25: Day 27: Eigenvalues & eigenvectors | F25: Linear Algebra | GATE CSE Complete Course · GO Classes for GATE CS (instructor not named in playlist) | G25: Search this lecture ▶ | H25: Uni-only: backtracking, branch & bound, NP-completeness | I25: Not in GATE 2027 syllabus but likely in your IPU DAA paper: N-Queens, graph colouring, branch & bound, P/NP/NP-complete, reductions (SAT, vertex cover). | J25: DSA - Abdul Bari · Abdul Bari | K25: Search this lecture ▶ | L25: Algorithms - Revision, GATE PYQs Complete Analysis | GO Classes | Sachin Mittal · Sachin Mittal (GO Classes) | M25: CLRS ch 34 (overview) | N25: GO-PDFs → Algorithms → Collect last 3 yrs IPU DAA papers; solve the NP/backtracking questions | O25: 3 | P25: Not Started
N26: Total planned hours | O26: =SUM(O13:O25) -> 39

Sheet 4 Compiler Design
A1: Compiler Design – day-by-day plan
A2: GATE + Uni (CIC-303 CD, 17 Dec) | The STATUS column here tracks only THIS subject. Maths is tracked in sheet 7, Aptitude in sheet 8.
A4: Playlists & teachers
A5: Main playlist | D5: Compiler Design - GATE Computer Science Classes · Prof. Ravindrababu Ravula [49 videos]
A6: Revision / PYQ playlist | D6: Compiler Design (GO Classes – GATE PYQs & revision) · GO Classes for GATE CS (instructor not named in playlist) [22 videos]
A7: More | D7: Compiler Design : Intermediate Code & Code Optimization | Local Optimization | Dataflow Analysis | Liveness Analysis · GO Classes for GATE CS (instructor not named in playlist) [10 videos]
A8: More | D8: CS3300 Compiler Design (IIT Madras) · Dr. Rupesh Nasre, IIT Madras [48 videos]
A9: Topic-wise PYQs | D9: GATE Overflow GO-PDFs (2025) → open 'Compiler Design'
A10: Textbook | D10: Dragon Book (Aho, Lam, Sethi, Ullman, 2E) – chapters given per day
A11: Free tests | D11: GO2019 Compiler 1 – Parsing | E11: Compiler Design | F11: Compilers GATE2020 PG-1 | G11: Compilers GATE2020 PG-2 | H11: Compilers GATE2020 PG-3
A13: Day # | B13: Date | C13: Day | D13: Aptitude today (reference – track in sheet 8) | E13: MATHS lecture today (reference – track in sheet 7) | F13: Maths playlist · teacher (click) | G13: Maths video search ▶ | H13: MAIN lecture topic | I13: What's covered | J13: Main playlist · teacher (click) | K13: Main video search ▶ | L13: Also use today: PYQ / extra playlist · teacher (click) | M13: Textbook | N13: Practice (PYQs) | O13: Planned hrs (whole day) | P13: STATUS – this subject only | Q13: Notes
A14: 1 | B14: 46339 | C14: =TEXT(B14,"ddd") -> Fri | D14: Aptitude: Spatial reasoning: paper folding, cubes, patterns – 8-10 easy Qs (20 min). Source: Complete Course on General Aptitude for GATE & ESE 2025 & 2026 (Unacademy) | E14: Day 28: Eigen properties: Cayley-Hamilton & diagonalisation | F14: Linear Algebra | GATE CSE Complete Course · GO Classes for GATE CS (instructor not named in playlist) | G14: Search this lecture ▶ | H14: Compiler phases & lexical analysis | I14: Phases of a compiler, tokens/lexemes/patterns, regex to DFA recap, lexical errors, symbol table, lex tool. | J14: Compiler Design - GATE Computer Science Classes · Prof. Ravindrababu Ravula | K14: Search this lecture ▶ | L14: Compiler Design (GO Classes – GATE PYQs & revision) · GO Classes for GATE CS (instructor not named in playlist) | M14: Dragon ch 1, 3 | N14: GO-PDFs → Compiler Design → Lexical analysis PYQs – 10 Qs | O14: 3 | P14: Not Started
A15: 2 | B15: 46340 | C15: =TEXT(B15,"ddd") -> Sat | D15: Aptitude: Percentages & ratios – 8-10 easy Qs (20 min). Source: Complete Course on General Aptitude for GATE & ESE 2025 & 2026 (Unacademy) | E15: Day 29: LU decomposition + LA problem-solving | F15: Linear Algebra | GATE CSE Complete Course · GO Classes for GATE CS (instructor not named in playlist) | G15: Search this lecture ▶ | H15: Parsing I: top-down & LL(1) | I15: CFG recap, ambiguity, left recursion elimination, left factoring, FIRST & FOLLOW, LL(1) table construction. | J15: Compiler Design - GATE Computer Science Classes · Prof. Ravindrababu Ravula | K15: Search this lecture ▶ | L15: Compiler Design (GO Classes – GATE PYQs & revision) · GO Classes for GATE CS (instructor not named in playlist) | M15: Dragon ch 4.1-4.4 | N15: GO-PDFs → Compiler Design → FIRST/FOLLOW & LL(1) PYQs – 15 Qs | O15: 3 | P15: Not Started | Q15: Finish with 8-10 LA PYQs.
A16: 3 | B16: 46342 | C16: =TEXT(B16,"ddd") -> Mon | D16: Aptitude: Time & work – 8-10 easy Qs (20 min). Source: Complete Course on General Aptitude for GATE & ESE 2025 & 2026 (Unacademy) | E16: Day 30: Probability basics | F16: Probability and Statistics for Engineering | GATE | gradeup · Channel: Algorithm Unlocked (instructor not named in playlist) | G16: Search this lecture ▶ | H16: Parsing II: bottom-up, LR(0) & SLR(1) | I16: Shift-reduce parsing, handles, LR items, closure/goto, LR(0) and SLR(1) tables and conflicts. | J16: Compiler Design - GATE Computer Science Classes · Prof. Ravindrababu Ravula | K16: Search this lecture ▶ | L16: Compiler Design (GO Classes – GATE PYQs & revision) · GO Classes for GATE CS (instructor not named in playlist) | M16: Dragon ch 4.5-4.6 | N16: GO-PDFs → Compiler Design → LR(0)/SLR PYQs – 12 Qs | O16: 3 | P16: Not Started
A17: 4 | B17: 46343 | C17: =TEXT(B17,"ddd") -> Tue | D17: Aptitude: Speed, time & distance – 8-10 easy Qs (20 min). Source: Complete Course on General Aptitude for GATE & ESE 2025 & 2026 (Unacademy) | E17: Day 31: Conditional probability & independence | F17: Probability and Statistics for Engineering | GATE | gradeup · Channel: Algorithm Unlocked (instructor not named in playlist) | G17: Search this lecture ▶ | H17: Parsing III: CLR(1), LALR(1), operator precedence | I17: CLR(1) items, LALR(1) merging, parser power hierarchy, SR/RR conflicts, operator-precedence parsing (uni). | J17: Compiler Design - GATE Computer Science Classes · Prof. Ravindrababu Ravula | K17: Search this lecture ▶ | L17: Compiler Design (GO Classes – GATE PYQs & revision) · GO Classes for GATE CS (instructor not named in playlist) | M17: Dragon ch 4.7-4.8 | N17: GO-PDFs → Compiler Design → CLR/LALR PYQs – 12 Qs | O17: 3 | P17: Not Started
A18: 5 | B18: 46344 | C18: =TEXT(B18,"ddd") -> Wed | D18: Aptitude: Profit/loss & averages – 8-10 easy Qs (20 min). Source: Complete Course on General Aptitude for GATE & ESE 2025 & 2026 (Unacademy) | E18: Day 32: Bayes' theorem & total probability | F18: Probability and Statistics for Engineering | GATE | gradeup · Channel: Algorithm Unlocked (instructor not named in playlist) | G18: Search this lecture ▶ | H18: Syntax-directed translation | I18: SDD & SDT, synthesized vs inherited attributes, S-attributed & L-attributed, dependency graph, evaluation order. | J18: Compiler Design - GATE Computer Science Classes · Prof. Ravindrababu Ravula | K18: Search this lecture ▶ | L18: Compiler Design (GO Classes – GATE PYQs & revision) · GO Classes for GATE CS (instructor not named in playlist) | M18: Dragon ch 5 | N18: GO-PDFs → Compiler Design → SDT PYQs – 10 Qs | O18: 3 | P18: Not Started
A19: 6 | B19: 46345 | C19: =TEXT(B19,"ddd") -> Thu | D19: Aptitude: Number series & sequences – 8-10 easy Qs (20 min). Source: Complete Course on General Aptitude for GATE & ESE 2025 & 2026 (Unacademy) | E19: Day 33: Random variables: PMF, PDF, CDF | F19: Probability and Statistics for Engineering | GATE | gradeup · Channel: Algorithm Unlocked (instructor not named in playlist) | G19: Search this lecture ▶ | H19: Intermediate code & runtime environments | I19: Three-address code, quadruples/triples, DAG, backpatching; activation records, stack/heap allocation, parameter passing, scope. | J19: Compiler Design - GATE Computer Science Classes · Prof. Ravindrababu Ravula | K19: Search this lecture ▶ | L19: Compiler Design : Intermediate Code & Code Optimization | Local Optimization | Dataflow Analysis | Liveness Analysis · GO Classes for GATE CS (instructor not named in playlist) + Compiler Design (GO Classes – GATE PYQs & revision) · GO Classes for GATE CS (instructor not named in playlist) | M19: Dragon ch 6, 7 | N19: GO-PDFs → Compiler Design → ICG & runtime PYQs – 12 Qs | O19: 3 | P19: Not Started
A20: 7 | B20: 46346 | C20: =TEXT(B20,"ddd") -> Fri | D20: Aptitude: Basic counting & probability (aptitude level) – 8-10 easy Qs (20 min). Source: Complete Course on General Aptitude for GATE & ESE 2025 & 2026 (Unacademy) | E20: Day 34: Expectation, variance & standard deviation | F20: Probability and Statistics for Engineering | GATE | gradeup · Channel: Algorithm Unlocked (instructor not named in playlist) | G20: Search this lecture ▶ | H20: Code optimisation & data-flow analysis | I20: Basic blocks & flow graph, local optimisation, constant propagation, liveness analysis, common-subexpression elimination, GEN/KILL. | J20: Compiler Design - GATE Computer Science Classes · Prof. Ravindrababu Ravula | K20: Search this lecture ▶ | L20: Compiler Design : Intermediate Code & Code Optimization | Local Optimization | Dataflow Analysis | Liveness Analysis · GO Classes for GATE CS (instructor not named in playlist) + Compiler Design (GO Classes – GATE PYQs & revision) · GO Classes for GATE CS (instructor not named in playlist) | M20: Dragon ch 8.4-8.5, 9.1-9.2 | N20: GO-PDFs → Compiler Design → Optimisation PYQs – 12 Qs + full CD recap | O20: 3 | P20: Not Started
N21: Total planned hours | O21: =SUM(O14:O20) -> 21

Sheet 5 Operating Systems
A1: Operating Systems – day-by-day plan
A2: GATE + Uni (CIC-305 OS, 19 Dec) | The STATUS column here tracks only THIS subject. Maths is tracked in sheet 7, Aptitude in sheet 8.
A4: Playlists & teachers
A5: Main playlist | D5: Operating System | GATE 2022 | Vishavdeep Sir · Vishavdeep (Vishvadeep) Sir [62 videos]
A6: Revision / PYQ playlist | D6: Operating Systems GATE PYQs, Revision Playlist · GO Classes for GATE CS (instructor not named in playlist) [11 videos]
A7: More | D7: Introduction to Operating Systems | IIT Madras (NPTEL) · NPTEL-NOC IITM (instructor not named in playlist) [39 videos]
A8: Topic-wise PYQs | D8: GATE Overflow GO-PDFs (2025) → open 'Operating System'
A9: Textbook | D9: Silberschatz, Galvin, Gagne – Operating System Concepts (9E)
A10: Free tests | D10: GO2017 OS 1 | E10: GO2017 OS 2 | F10: GO2017 OS 3 | G10: OS GATE2020 Previous GATE 2
A12: Day # | B12: Date | C12: Day | D12: Aptitude today (reference – track in sheet 8) | E12: MATHS lecture today (reference – track in sheet 7) | F12: Maths playlist · teacher (click) | G12: Maths video search ▶ | H12: MAIN lecture topic | I12: What's covered | J12: Main playlist · teacher (click) | K12: Main video search ▶ | L12: Also use today: PYQ / extra playlist · teacher (click) | M12: Textbook | N12: Practice (PYQs) | O12: Planned hrs (whole day) | P12: STATUS – this subject only | Q12: Notes
A13: 1 | B13: 46347 | C13: =TEXT(B13,"ddd") -> Sat | D13: Aptitude: Data interpretation (tables, bar charts) – 8-10 easy Qs (20 min). Source: Complete Course on General Aptitude for GATE & ESE 2025 & 2026 (Unacademy) | E13: Day 35: Binomial distribution | F13: Probability and Statistics for Engineering | GATE | gradeup · Channel: Algorithm Unlocked (instructor not named in playlist) | G13: Search this lecture ▶ | H13: OS basics, system calls & processes | I13: OS functions & types, kernel/user mode, system calls, process concept, PCB, states, context switch, fork() output questions. | J13: Operating System | GATE 2022 | Vishavdeep Sir · Vishavdeep (Vishvadeep) Sir | K13: Search this lecture ▶ | L13: Operating Systems GATE PYQs, Revision Playlist · GO Classes for GATE CS (instructor not named in playlist) | M13: Silberschatz ch 2.1-2.5, 3 | N13: GO-PDFs → Operating System → fork()/process PYQs – 10 Qs | O13: 3 | P13: Not Started
A14: 2 | B14: 46349 | C14: =TEXT(B14,"ddd") -> Mon | D14: Aptitude: Verbal: tenses & subject-verb agreement – 8-10 easy Qs (20 min). Source: GATE Overflow – verbal aptitude lessons | E14: Day 36: Poisson distribution | F14: Probability and Statistics for Engineering | GATE | gradeup · Channel: Algorithm Unlocked (instructor not named in playlist) | G14: Search this lecture ▶ | H14: Threads & inter-process communication | I14: User vs kernel threads, multithreading models, pthreads, IPC: shared memory, message passing, pipes. | J14: Operating System | GATE 2022 | Vishavdeep Sir · Vishavdeep (Vishvadeep) Sir | K14: Search this lecture ▶ | L14: Operating Systems GATE PYQs, Revision Playlist · GO Classes for GATE CS (instructor not named in playlist) | M14: Silberschatz ch 4.1-4.3, 4.6; ch 3 (IPC) | N14: GO-PDFs → Operating System → Threads/IPC PYQs – 10 Qs | O14: 3 | P14: Not Started
A15: 3 | B15: 46350 | C15: =TEXT(B15,"ddd") -> Tue | D15: Aptitude: Verbal: sentence completion & prepositions – 8-10 easy Qs (20 min). Source: GATE Overflow – verbal aptitude lessons | E15: Day 37: Uniform distribution | F15: Probability and Statistics for Engineering | GATE | gradeup · Channel: Algorithm Unlocked (instructor not named in playlist) | G15: Search this lecture ▶ | H15: CPU scheduling I | I15: Scheduling criteria; FCFS, SJF, SRTF, priority; Gantt charts, waiting/turnaround time, convoy effect, starvation. | J15: Operating System | GATE 2022 | Vishavdeep Sir · Vishavdeep (Vishvadeep) Sir | K15: Search this lecture ▶ | L15: Operating Systems GATE PYQs, Revision Playlist · GO Classes for GATE CS (instructor not named in playlist) | M15: Silberschatz ch 5.1-5.3 | N15: GO-PDFs → Operating System → FCFS/SJF/SRTF numericals – 12 Qs | O15: 3 | P15: Not Started
A16: 4 | B16: 46351 | C16: =TEXT(B16,"ddd") -> Wed | D16: Aptitude: Verbal: synonyms, antonyms & idioms – 8-10 easy Qs (20 min). Source: GATE Overflow – verbal aptitude lessons | E16: Day 38: Exponential distribution | F16: Probability and Statistics for Engineering | GATE | gradeup · Channel: Algorithm Unlocked (instructor not named in playlist) | G16: Search this lecture ▶ | H16: CPU scheduling II | I16: Round robin (time quantum effects), multilevel queue & feedback queue, mixed numericals with I/O bursts. | J16: Operating System | GATE 2022 | Vishavdeep Sir · Vishavdeep (Vishvadeep) Sir | K16: Search this lecture ▶ | L16: Operating Systems GATE PYQs, Revision Playlist · GO Classes for GATE CS (instructor not named in playlist) | M16: Silberschatz ch 5 | N16: GO-PDFs → Operating System → RR/MLFQ numericals – 12 Qs | O16: 3 | P16: Not Started
A17: 5 | B17: 46352 | C17: =TEXT(B17,"ddd") -> Thu | D17: Aptitude: Reading comprehension (1 passage) – 8-10 easy Qs (20 min). Source: GATE Overflow – verbal aptitude lessons | E17: Day 39: Normal distribution | F17: Probability and Statistics for Engineering | GATE | gradeup · Channel: Algorithm Unlocked (instructor not named in playlist) | G17: Search this lecture ▶ | H17: Process synchronisation I | I17: Race condition, critical-section requirements, Peterson, Test-and-Set, mutex, semaphores (binary/counting). | J17: Operating System | GATE 2022 | Vishavdeep Sir · Vishavdeep (Vishvadeep) Sir | K17: Search this lecture ▶ | L17: Operating Systems GATE PYQs, Revision Playlist · GO Classes for GATE CS (instructor not named in playlist) | M17: Silberschatz ch 6.1-6.6 | N17: GO-PDFs → Operating System → Critical section & semaphore PYQs – 12 Qs | O17: 2.5 | P17: Not Started
A18: 6 | B18: 46353 | C18: =TEXT(B18,"ddd") -> Fri | D18: Aptitude: Para-jumbles & sentence ordering – 8-10 easy Qs (20 min). Source: GATE Overflow – verbal aptitude lessons | E18: Day 40: Statistics: mean, median, mode & standard deviation | F18: Introduction to probability and Statistics (NPTEL) · NPTEL-NOC IITM (instructor not named in playlist) | G18: Search this lecture ▶ | H18: Process synchronisation II | I18: Producer-consumer, readers-writers, dining philosophers, monitors; semaphore code-tracing questions. | J18: Operating System | GATE 2022 | Vishavdeep Sir · Vishavdeep (Vishvadeep) Sir | K18: Search this lecture ▶ | L18: Operating Systems GATE PYQs, Revision Playlist · GO Classes for GATE CS (instructor not named in playlist) | M18: Silberschatz ch 6.7-6.10 | N18: GO-PDFs → Operating System → Classical sync problem PYQs – 12 Qs | O18: 2.5 | P18: Not Started
A19: 7 | B19: 46354 | C19: =TEXT(B19,"ddd") -> Sat | D19: Aptitude: Logical reasoning: arrangements & puzzles – 8-10 easy Qs (20 min). Source: Complete Course on General Aptitude for GATE & ESE 2025 & 2026 (Unacademy) | E19: Day 41: Probability problem-solving: Bayes + distributions | F19: Probability and Statistics for Engineering | GATE | gradeup · Channel: Algorithm Unlocked (instructor not named in playlist) | G19: Search this lecture ▶ | H19: Deadlocks | I19: Four necessary conditions, resource-allocation graph, prevention, avoidance (Banker's algorithm), detection, recovery. | J19: Operating System | GATE 2022 | Vishavdeep Sir · Vishavdeep (Vishvadeep) Sir | K19: Search this lecture ▶ | L19: Operating Systems GATE PYQs, Revision Playlist · GO Classes for GATE CS (instructor not named in playlist) | M19: Silberschatz ch 7 | N19: GO-PDFs → Operating System → Banker's/deadlock PYQs – 12 Qs | O19: 2.5 | P19: Not Started | Q19: Spend most of today on PYQs.
A20: 8 | B20: 46356 | C20: =TEXT(B20,"ddd") -> Mon | D20: Aptitude: Spatial reasoning: paper folding, cubes, patterns – 8-10 easy Qs (20 min). Source: Complete Course on General Aptitude for GATE & ESE 2025 & 2026 (Unacademy) | E20: Day 42: Calculus: limits | F20: Calculus of One Variable - Joydeep Das | IIT Kanpur - NPTEL · Joydeep Das, IIT Kanpur | G20: Search this lecture ▶ | H20: Memory management: paging & segmentation | I20: Contiguous allocation, fragmentation, paging, page table size, TLB & effective access time, segmentation, multilevel paging. | J20: Operating System | GATE 2022 | Vishavdeep Sir · Vishavdeep (Vishvadeep) Sir | K20: Search this lecture ▶ | L20: Operating Systems GATE PYQs, Revision Playlist · GO Classes for GATE CS (instructor not named in playlist) | M20: Silberschatz ch 8.1-8.6 | N20: GO-PDFs → Operating System → Paging/TLB/EAT numericals – 15 Qs | O20: 2.5 | P20: Not Started
A21: 9 | B21: 46357 | C21: =TEXT(B21,"ddd") -> Tue | D21: Aptitude: Percentages & ratios – 8-10 easy Qs (20 min). Source: Complete Course on General Aptitude for GATE & ESE 2025 & 2026 (Unacademy) | E21: Day 43: Calculus: continuity | F21: Calculus of One Variable - Joydeep Das | IIT Kanpur - NPTEL · Joydeep Das, IIT Kanpur | G21: Search this lecture ▶ | H21: Virtual memory | I21: Demand paging, page faults, FIFO/LRU/Optimal replacement, Belady's anomaly, thrashing, working set, effective access time with faults. | J21: Operating System | GATE 2022 | Vishavdeep Sir · Vishavdeep (Vishvadeep) Sir | K21: Search this lecture ▶ | L21: Operating Systems GATE PYQs, Revision Playlist · GO Classes for GATE CS (instructor not named in playlist) | M21: Silberschatz ch 9.1-9.6, 9.9 | N21: GO-PDFs → Operating System → Page replacement & VM PYQs – 15 Qs | O21: 2.5 | P21: Not Started
A22: 10 | B22: 46358 | C22: =TEXT(B22,"ddd") -> Wed | D22: Aptitude: Time & work – 8-10 easy Qs (20 min). Source: Complete Course on General Aptitude for GATE & ESE 2025 & 2026 (Unacademy) | E22: Day 44: Calculus: differentiability | F22: Calculus of One Variable - Joydeep Das | IIT Kanpur - NPTEL · Joydeep Das, IIT Kanpur | G22: Search this lecture ▶ | H22: File systems, disk scheduling & I/O | I22: File concept, directory structure, allocation (contiguous/linked/indexed/inode), free-space mgmt, disk scheduling (FCFS, SSTF, SCAN, C-SCAN, LOOK), I/O. | J22: Operating System | GATE 2022 | Vishavdeep Sir · Vishavdeep (Vishvadeep) Sir | K22: Search this lecture ▶ | L22: Operating Systems GATE PYQs, Revision Playlist · GO Classes for GATE CS (instructor not named in playlist) | M22: Silberschatz ch 10, 11.1-11.5, 12.1-12.6 | N22: GO-PDFs → Operating System → File system & disk-scheduling PYQs – 12 Qs + full OS recap | O22: 2.5 | P22: Not Started
N23: Total planned hours | O23: =SUM(O13:O22) -> 27

Sheet 6 Computer Networks
A1: Computer Networks – day-by-day plan
A2: GATE + Uni (CIC-307 CN, 22 Dec) | The STATUS column here tracks only THIS subject. Maths is tracked in sheet 7, Aptitude in sheet 8.
A4: Playlists & teachers
A5: Main playlist | D5: Computer Networks (CN) for GATE — Complete Playlist · Amit Khurana [202 videos]
A6: Revision / PYQ playlist | D6: Computer Networks GATE PYQs, Revision Playlist · GO Classes for GATE CS (instructor not named in playlist) [23 videos]
A7: More | D7: Computer Networks and Internet Protocol (NPTEL IIT Kharagpur) · NPTEL IIT Kharagpur (instructor not named in playlist) [61 videos]
A8: Topic-wise PYQs | D8: GATE Overflow GO-PDFs (2025) → open 'Computer Network'
A9: Textbook | D9: Forouzan – Data Communications & Networking (5E); chapter numbers as listed in your resource PDF
A10: Free tests | D10: Computer Networks (GO) | E10: CN GATE2020 PG-1 | F10: CN GATE2020 PG-2
A12: Day # | B12: Date | C12: Day | D12: Aptitude today (reference – track in sheet 8) | E12: MATHS lecture today (reference – track in sheet 7) | F12: Maths playlist · teacher (click) | G12: Maths video search ▶ | H12: MAIN lecture topic | I12: What's covered | J12: Main playlist · teacher (click) | K12: Main video search ▶ | L12: Also use today: PYQ / extra playlist · teacher (click) | M12: Textbook | N12: Practice (PYQs) | O12: Planned hrs (whole day) | P12: STATUS – this subject only | Q12: Notes
A13: 1 | B13: 46359 | C13: =TEXT(B13,"ddd") -> Thu | D13: Aptitude: Speed, time & distance – 8-10 easy Qs (20 min). Source: Complete Course on General Aptitude for GATE & ESE 2025 & 2026 (Unacademy) | E13: Day 45: Mean value theorems | F13: Calculus of One Variable - Joydeep Das | IIT Kanpur - NPTEL · Joydeep Das, IIT Kanpur | G13: Search this lecture ▶ | H13: Layering, switching & performance metrics | I13: OSI vs TCP/IP layers, circuit/packet/virtual-circuit switching, transmission/propagation/queuing delay, throughput, bandwidth-delay product. | J13: Computer Networks (CN) for GATE — Complete Playlist · Amit Khurana | K13: Search this lecture ▶ | L13: Computer Networks GATE PYQs, Revision Playlist · GO Classes for GATE CS (instructor not named in playlist) | M13: Forouzan ch 1.1-1.3, 2, 3.6, 8 | N13: GO-PDFs → Computer Network → Layering & delay numericals – 10 Qs | O13: 2.5 | P13: Not Started
A14: 2 | B14: 46360 | C14: =TEXT(B14,"ddd") -> Fri | D14: Aptitude: Profit/loss & averages – 8-10 easy Qs (20 min). Source: Complete Course on General Aptitude for GATE & ESE 2025 & 2026 (Unacademy) | E14: Day 46: Maxima & minima | F14: Calculus of One Variable - Joydeep Das | IIT Kanpur - NPTEL · Joydeep Das, IIT Kanpur | G14: Search this lecture ▶ | H14: Data link I: framing & error detection | I14: Framing, parity, checksum, CRC (polynomial division), Hamming code and distance. | J14: Computer Networks (CN) for GATE — Complete Playlist · Amit Khurana | K14: Search this lecture ▶ | L14: Computer Networks GATE PYQs, Revision Playlist · GO Classes for GATE CS (instructor not named in playlist) | M14: Forouzan ch 10 | N14: GO-PDFs → Computer Network → CRC/checksum/Hamming PYQs – 12 Qs | O14: 2.5 | P14: Not Started
A15: 3 | B15: 46361 | C15: =TEXT(B15,"ddd") -> Sat | D15: Aptitude: Number series & sequences – 8-10 easy Qs (20 min). Source: Complete Course on General Aptitude for GATE & ESE 2025 & 2026 (Unacademy) | E15: Day 47: Integration I | F15: Calculus of One Variable - Joydeep Das | IIT Kanpur - NPTEL · Joydeep Das, IIT Kanpur | G15: Search this lecture ▶ | H15: Data link II: flow control & ARQ | I15: Stop-and-wait, Go-Back-N, Selective Repeat, window sizes, sequence-number bits, link efficiency/utilisation. | J15: Computer Networks (CN) for GATE — Complete Playlist · Amit Khurana | K15: Search this lecture ▶ | L15: Computer Networks GATE PYQs, Revision Playlist · GO Classes for GATE CS (instructor not named in playlist) | M15: Forouzan ch 11.1-11.2 | N15: GO-PDFs → Computer Network → Sliding-window & efficiency numericals – 15 Qs | O15: 2.5 | P15: Not Started
A16: 4 | B16: 46363 | C16: =TEXT(B16,"ddd") -> Mon | D16: Aptitude: Basic counting & probability (aptitude level) – 8-10 easy Qs (20 min). Source: Complete Course on General Aptitude for GATE & ESE 2025 & 2026 (Unacademy) | E16: Day 48: Integration II | F16: Calculus of One Variable - Joydeep Das | IIT Kanpur - NPTEL · Joydeep Das, IIT Kanpur | G16: Search this lecture ▶ | H16: MAC & Ethernet | I16: Pure/slotted ALOHA, CSMA, CSMA/CD, minimum frame size, Ethernet frame, hubs/bridges/switches, VLAN overview. | J16: Computer Networks (CN) for GATE — Complete Playlist · Amit Khurana | K16: Search this lecture ▶ | L16: Computer Networks GATE PYQs, Revision Playlist · GO Classes for GATE CS (instructor not named in playlist) | M16: Forouzan ch 12, 13.1-13.2 | N16: GO-PDFs → Computer Network → ALOHA/CSMA-CD PYQs – 12 Qs | O16: 3 | P16: Not Started
A17: 5 | B17: 46364 | C17: =TEXT(B17,"ddd") -> Tue | D17: Aptitude: Data interpretation (tables, bar charts) – 8-10 easy Qs (20 min). Source: Complete Course on General Aptitude for GATE & ESE 2025 & 2026 (Unacademy) | E17: Day 49: Integration III & calculus revision | F17: Calculus Complete Playlist | Engineering Mathematics · GO Classes for GATE CS (instructor not named in playlist) | G17: Search this lecture ▶ | H17: Network layer I: IPv4, subnetting, CIDR, NAT | I17: IPv4 classes, subnetting & VLSM, CIDR aggregation, NAT, fragmentation (MTU/offset), ARP, ICMP, DHCP. | J17: Computer Networks (CN) for GATE — Complete Playlist · Amit Khurana | K17: Search this lecture ▶ | L17: Computer Networks GATE PYQs, Revision Playlist · GO Classes for GATE CS (instructor not named in playlist) | M17: Forouzan ch 18-19.2 | N17: GO-PDFs → Computer Network → Subnetting/CIDR/fragmentation PYQs – 15 Qs | O17: 3 | P17: Not Started
A18: 6 | B18: 46365 | C18: =TEXT(B18,"ddd") -> Wed | D18: Aptitude: Verbal: tenses & subject-verb agreement – 8-10 easy Qs (20 min). Source: GATE Overflow – verbal aptitude lessons | E18: Day 50: Calculus problem-solving with PYQs | F18: Calculus Complete Playlist | Engineering Mathematics · GO Classes for GATE CS (instructor not named in playlist) | G18: Search this lecture ▶ | H18: Network layer II: routing | I18: Distance-vector (Bellman-Ford, count-to-infinity), link-state (Dijkstra), RIP/OSPF/BGP, intra vs inter-domain (IPv6 basics for uni). | J18: Computer Networks (CN) for GATE — Complete Playlist · Amit Khurana | K18: Search this lecture ▶ | L18: Computer Networks GATE PYQs, Revision Playlist · GO Classes for GATE CS (instructor not named in playlist) | M18: Forouzan ch 20-21.2 | N18: GO-PDFs → Computer Network → Routing PYQs – 12 Qs | O18: 3 | P18: Not Started
A19: 7 | B19: 46366 | C19: =TEXT(B19,"ddd") -> Thu | D19: Aptitude: Verbal: sentence completion & prepositions – 8-10 easy Qs (20 min). Source: GATE Overflow – verbal aptitude lessons | E19: Day 51: Discrete Maths consolidation (PYQs) | F19: Discrete Mathematics – Revision & PYQs video solutions (title not verified; from your resource PDF) · Not verified | G19: Search this lecture ▶ | H19: Transport layer: UDP, TCP & sockets | I19: UDP, TCP segment, 3-way handshake & teardown, TCP flow control, congestion control (slow start, AIMD, fast retransmit), timeouts, socket API. | J19: Computer Networks (CN) for GATE — Complete Playlist · Amit Khurana | K19: Search this lecture ▶ | L19: Computer Networks GATE PYQs, Revision Playlist · GO Classes for GATE CS (instructor not named in playlist) | M19: Forouzan ch 23-24.3 | N19: GO-PDFs → Computer Network → TCP congestion/flow-control PYQs – 15 Qs | O19: 3 | P19: Not Started | Q19: Open the PYQ video solutions and attempt each question first.
A20: 8 | B20: 46377 | C20: =TEXT(B20,"ddd") -> Mon | D20: Aptitude: none today – Day 52 is scheduled on 29 Dec (see sheet 8). | E20: Maths: none today – Day 52 (M52) is scheduled on 29 Dec (see sheet 7). | F20: Linear Algebra | GATE CSE Complete Course · GO Classes for GATE CS (instructor not named in playlist) | G20: Search this lecture ▶ | H20: Application layer: DNS, HTTP & security basics | I20: DNS hierarchy & resolution, HTTP persistent/non-persistent, SMTP/FTP/POP, cookies; (uni: basic cryptography & firewalls). | J20: Computer Networks (CN) for GATE — Complete Playlist · Amit Khurana | K20: Search this lecture ▶ | L20: Computer Networks GATE PYQs, Revision Playlist · GO Classes for GATE CS (instructor not named in playlist) | M20: Forouzan ch 25.1-25.2, 26 | N20: GO-PDFs → Computer Network → DNS/HTTP PYQs – 10 Qs + full CN recap | O20: 3 | P20: Not Started | Q20: Moved to 21 Dec because of the late start. Finish this lecture first, then do the CN theory revision.
N21: Total planned hours | O21: =SUM(O13:O20) -> 22.5

Sheet 7 Engineering Maths
A1: Engineering Mathematics – exactly ONE lecture per day (13 Oct – 29 Dec)
A2: Order: Discrete Maths (22 days) → Linear Algebra (7) → Probability & Statistics (12) → Calculus (9) → PYQ consolidation (2). Dec 29-30 revisit maths in the wrap-up sheet.
A4: Day # | B4: Date | C4: Day | D4: Lecture topic | E4: What's covered | F4: Playlist · teacher (click) | G4: Video search ▶ | H4: Subject studied the same day | I4: Quick practice | J4: Planned min | K4: Status | L4: Notes
A5: 1 | B5: 46308 | C5: =TEXT(B5,"ddd") -> Tue | D5: Propositional logic I: propositions, connectives, truth tables | E5: Propositions, AND/OR/NOT/IMPLIES/IFF, truth tables, converse/inverse/contrapositive. | F5: Propositional Logic - Complete Summary, All GATE PYQs & Practice Questions | Discrete Mathematics · GO Classes for GATE CS (instructor not named in playlist) | G5: Search this lecture ▶ | H5: C Programming (Day 1) | I5: GO-PDFs → Discrete Maths PYQs: 5-8 Qs (inside today's practice block) | J5: 30 | K5: Not Started
A6: 2 | B6: 46309 | C6: =TEXT(B6,"ddd") -> Wed | D6: Propositional logic II: equivalences, tautology, normal forms | E6: Logical equivalences, tautology/contradiction, CNF/DNF, simplification. | F6: Propositional Logic - Complete Summary, All GATE PYQs & Practice Questions | Discrete Mathematics · GO Classes for GATE CS (instructor not named in playlist) | G6: Search this lecture ▶ | H6: C Programming (Day 2) | I6: GO-PDFs → Discrete Maths PYQs: 5-8 Qs (inside today's practice block) | J6: 30 | K6: Not Started
A7: 3 | B7: 46310 | C7: =TEXT(B7,"ddd") -> Thu | D7: Propositional logic III: inference, validity, functional completeness | E7: Rules of inference, validity of arguments, satisfiability, NAND/NOR completeness. | F7: Propositional Logic - Complete Summary, All GATE PYQs & Practice Questions | Discrete Mathematics · GO Classes for GATE CS (instructor not named in playlist) | G7: Search this lecture ▶ | H7: C Programming (Day 3) | I7: GO-PDFs → Discrete Maths PYQs: 5-8 Qs (inside today's practice block) | J7: 30 | K7: Not Started
A8: 4 | B8: 46311 | C8: =TEXT(B8,"ddd") -> Fri | D8: First-order logic I: predicates & quantifiers | E8: Predicates, universal/existential quantifiers, free/bound variables. | F8: Propositional Logic - Complete Summary, All GATE PYQs & Practice Questions | Discrete Mathematics · GO Classes for GATE CS (instructor not named in playlist) | G8: Search this lecture ▶ | H8: C Programming (Day 4) | I8: GO-PDFs → Discrete Maths PYQs: 5-8 Qs (inside today's practice block) | J8: 30 | K8: Not Started | L8: If FOL isn't inside this playlist, search 'GO Classes first order logic' (not in your resource PDF).
A9: 5 | B9: 46312 | C9: =TEXT(B9,"ddd") -> Sat | D9: First-order logic II: translation & nested quantifiers | E9: English ↔ FOL, nested quantifiers, quantifier negation, validity. | F9: Propositional Logic - Complete Summary, All GATE PYQs & Practice Questions | Discrete Mathematics · GO Classes for GATE CS (instructor not named in playlist) | G9: Search this lecture ▶ | H9: C Programming (Day 5) | I9: GO-PDFs → Discrete Maths PYQs: 5-8 Qs (inside today's practice block) | J9: 30 | K9: Not Started | L9: Same note as day 4.
A10: 6 | B10: 46314 | C10: =TEXT(B10,"ddd") -> Mon | D10: Sets: operations, power set, cardinality | E10: Set algebra, Venn diagrams, power set, inclusion-exclusion for sets. | F10: Set Theory - GATE PYQs, Summary, Practice, Revision | Discrete Mathematics · GO Classes for GATE CS (instructor not named in playlist) | G10: Search this lecture ▶ | H10: Data Structures (Day 1) | I10: GO-PDFs → Discrete Maths PYQs: 5-8 Qs (inside today's practice block) | J10: 35 | K10: Not Started
A11: 7 | B11: 46315 | C11: =TEXT(B11,"ddd") -> Tue | D11: Relations I: types & representation | E11: Relation as set of pairs, reflexive/symmetric/antisymmetric/transitive, matrix form, composition. | F11: Set Theory - GATE PYQs, Summary, Practice, Revision | Discrete Mathematics · GO Classes for GATE CS (instructor not named in playlist) | G11: Search this lecture ▶ | H11: Data Structures (Day 2) | I11: GO-PDFs → Discrete Maths PYQs: 5-8 Qs (inside today's practice block) | J11: 35 | K11: Not Started | L11: Closest playlist from your PDF; if relations aren't covered, search 'GO Classes relations discrete mathematics'.
A12: 8 | B12: 46316 | C12: =TEXT(B12,"ddd") -> Wed | D12: Relations II: equivalence relations, partitions, closures | E12: Equivalence classes, partitions, counting relations, reflexive/symmetric/transitive closure. | F12: Set Theory - GATE PYQs, Summary, Practice, Revision | Discrete Mathematics · GO Classes for GATE CS (instructor not named in playlist) | G12: Search this lecture ▶ | H12: Data Structures (Day 3) | I12: GO-PDFs → Discrete Maths PYQs: 5-8 Qs (inside today's practice block) | J12: 35 | K12: Not Started | L12: Same note as day 7.
A13: 9 | B13: 46317 | C13: =TEXT(B13,"ddd") -> Thu | D13: Functions: injective, surjective, bijective | E13: One-one/onto/bijection, counting functions, composition, inverse, pigeonhole link. | F13: Set Theory - GATE PYQs, Summary, Practice, Revision | Discrete Mathematics · GO Classes for GATE CS (instructor not named in playlist) | G13: Search this lecture ▶ | H13: Data Structures (Day 4) | I13: GO-PDFs → Discrete Maths PYQs: 5-8 Qs (inside today's practice block) | J13: 35 | K13: Not Started | L13: Same note as day 7.
A14: 10 | B14: 46318 | C14: =TEXT(B14,"ddd") -> Fri | D14: Partial orders & Hasse diagrams | E14: Poset, Hasse diagram, chains/antichains, maximal/minimal/greatest/least elements. | F14: Set Theory - GATE PYQs, Summary, Practice, Revision | Discrete Mathematics · GO Classes for GATE CS (instructor not named in playlist) | G14: Search this lecture ▶ | H14: Data Structures (Day 5) | I14: GO-PDFs → Discrete Maths PYQs: 5-8 Qs (inside today's practice block) | J14: 35 | K14: Not Started | L14: Same note as day 7.
A15: 11 | B15: 46319 | C15: =TEXT(B15,"ddd") -> Sat | D15: Lattices | E15: LUB/GLB, lattice properties, distributive & complemented lattices, Boolean lattices. | F15: Set Theory - GATE PYQs, Summary, Practice, Revision | Discrete Mathematics · GO Classes for GATE CS (instructor not named in playlist) | G15: Search this lecture ▶ | H15: Data Structures (Day 6) | I15: GO-PDFs → Discrete Maths PYQs: 5-8 Qs (inside today's practice block) | J15: 35 | K15: Not Started | L15: Same note as day 7.
A16: 12 | B16: 46321 | C16: =TEXT(B16,"ddd") -> Mon | D16: Monoids, semigroups & groups | E16: Closure/associativity, identity/inverse, semigroup → monoid → group, abelian groups. | F16: Group Theory Complete Course - Abstract Algebra Course | Discrete Mathematics | Monoid, Groupoid, Semigroup, Abelian Group, Cyclic Group, Subgroup · GO Classes for GATE CS (instructor not named in playlist) | G16: Search this lecture ▶ | H16: Data Structures (Day 7) | I16: GO-PDFs → Discrete Maths PYQs: 5-8 Qs (inside today's practice block) | J16: 40 | K16: Not Started
A17: 13 | B17: 46322 | C17: =TEXT(B17,"ddd") -> Tue | D17: Subgroups, cyclic groups & Lagrange's theorem | E17: Subgroup tests, cyclic groups, order of elements, Lagrange's theorem, generators. | F17: Group Theory Complete Course - Abstract Algebra Course | Discrete Mathematics | Monoid, Groupoid, Semigroup, Abelian Group, Cyclic Group, Subgroup · GO Classes for GATE CS (instructor not named in playlist) | G17: Search this lecture ▶ | H17: Data Structures (Day 8) | I17: GO-PDFs → Discrete Maths PYQs: 5-8 Qs (inside today's practice block) | J17: 40 | K17: Not Started
A18: 14 | B18: 46323 | C18: =TEXT(B18,"ddd") -> Wed | D18: Graph basics: degrees, handshake, special graphs | E18: Degree sequences, handshake lemma, complete/bipartite/regular graphs, isomorphism. | F18: Graph Theory Complete Course - Discrete Mathematics | Complete Graph Theory Course | GO Classes · GO Classes for GATE CS (instructor not named in playlist) | G18: Search this lecture ▶ | H18: Data Structures (Day 9) | I18: GO-PDFs → Discrete Maths PYQs: 5-8 Qs (inside today's practice block) | J18: 40 | K18: Not Started
A19: 15 | B19: 46324 | C19: =TEXT(B19,"ddd") -> Thu | D19: Connectivity | E19: Walks/paths/cycles, connected components, cut vertices & bridges, k-connectivity. | F19: Graph Theory Complete Course - Discrete Mathematics | Complete Graph Theory Course | GO Classes · GO Classes for GATE CS (instructor not named in playlist) | G19: Search this lecture ▶ | H19: Algorithms (DAA) (Day 1) | I19: GO-PDFs → Discrete Maths PYQs: 5-8 Qs (inside today's practice block) | J19: 40 | K19: Not Started
A20: 16 | B20: 46325 | C20: =TEXT(B20,"ddd") -> Fri | D20: Trees, Euler & Hamiltonian graphs | E20: Tree properties, spanning trees count, Euler path/circuit, Hamiltonian conditions. | F20: Graph Theory Complete Course - Discrete Mathematics | Complete Graph Theory Course | GO Classes · GO Classes for GATE CS (instructor not named in playlist) | G20: Search this lecture ▶ | H20: Algorithms (DAA) (Day 2) | I20: GO-PDFs → Discrete Maths PYQs: 5-8 Qs (inside today's practice block) | J20: 40 | K20: Not Started
A21: 17 | B21: 46326 | C21: =TEXT(B21,"ddd") -> Sat | D21: Planar graphs & matching | E21: Euler's formula, planarity (Kuratowski), matchings, Hall's theorem. | F21: Graph Theory Complete Course - Discrete Mathematics | Complete Graph Theory Course | GO Classes · GO Classes for GATE CS (instructor not named in playlist) | G21: Search this lecture ▶ | H21: Algorithms (DAA) (Day 3) | I21: GO-PDFs → Discrete Maths PYQs: 5-8 Qs (inside today's practice block) | J21: 40 | K21: Not Started
A22: 18 | B22: 46328 | C22: =TEXT(B22,"ddd") -> Mon | D22: Graph colouring | E22: Chromatic number, bipartite test, cliques & independent sets, colouring bounds. | F22: Graph Theory Complete Course - Discrete Mathematics | Complete Graph Theory Course | GO Classes · GO Classes for GATE CS (instructor not named in playlist) | G22: Search this lecture ▶ | H22: Algorithms (DAA) (Day 4) | I22: GO-PDFs → Discrete Maths PYQs: 5-8 Qs (inside today's practice block) | J22: 40 | K22: Not Started
A23: 19 | B23: 46329 | C23: =TEXT(B23,"ddd") -> Tue | D23: Counting I: rules, permutations & combinations | E23: Sum/product rule, permutations, combinations, circular arrangements, repetition. | F23: Combinatorics Complete Course | Discrete Mathematics | Basic Counting Principles, Permutation & Combination | Generating Function, Recurrence Relation · GO Classes for GATE CS (instructor not named in playlist) | G23: Search this lecture ▶ | H23: Algorithms (DAA) (Day 5) | I23: GO-PDFs → Discrete Maths PYQs: 5-8 Qs (inside today's practice block) | J23: 40 | K23: Not Started
A24: 20 | B24: 46330 | C24: =TEXT(B24,"ddd") -> Wed | D24: Counting II: pigeonhole, inclusion-exclusion, stars & bars | E24: Pigeonhole principle, inclusion-exclusion, derangements, distributing objects. | F24: Combinatorics Complete Course | Discrete Mathematics | Basic Counting Principles, Permutation & Combination | Generating Function, Recurrence Relation · GO Classes for GATE CS (instructor not named in playlist) | G24: Search this lecture ▶ | H24: Algorithms (DAA) (Day 6) | I24: GO-PDFs → Discrete Maths PYQs: 5-8 Qs (inside today's practice block) | J24: 40 | K24: Not Started
A25: 21 | B25: 46331 | C25: =TEXT(B25,"ddd") -> Thu | D25: Recurrence relations | E25: Linear homogeneous & non-homogeneous recurrences, characteristic equation, solving & applications. | F25: Recurrence Relations in Discrete Mathematics | Complete Playlist | Applications of Recurrence Relations | GO Classes · GO Classes for GATE CS (instructor not named in playlist) | G25: Search this lecture ▶ | H25: Algorithms (DAA) (Day 7) | I25: GO-PDFs → Discrete Maths PYQs: 5-8 Qs (inside today's practice block) | J25: 40 | K25: Not Started
A26: 22 | B26: 46332 | C26: =TEXT(B26,"ddd") -> Fri | D26: Generating functions | E26: Ordinary generating functions, coefficient extraction, use for counting and recurrences. | F26: Combinatorics Complete Course | Discrete Mathematics | Basic Counting Principles, Permutation & Combination | Generating Function, Recurrence Relation · GO Classes for GATE CS (instructor not named in playlist) | G26: Search this lecture ▶ | H26: Algorithms (DAA) (Day 8) | I26: GO-PDFs → Discrete Maths PYQs: 5-8 Qs (inside today's practice block) | J26: 40 | K26: Not Started | L26: Generating-function videos sit near the end of this long playlist.
A27: 23 | B27: 46333 | C27: =TEXT(B27,"ddd") -> Sat | D27: Matrices: types & operations | E27: Matrix types, transpose, symmetric/skew, orthogonal, idempotent, multiplication. | F27: Linear Algebra | GATE CSE Complete Course · GO Classes for GATE CS (instructor not named in playlist) | G27: Search this lecture ▶ | H27: Algorithms (DAA) (Day 9) | I27: GO-PDFs → Linear Algebra PYQs: 5-8 Qs (inside today's practice block) | J27: 40 | K27: Not Started
A28: 24 | B28: 46335 | C28: =TEXT(B28,"ddd") -> Mon | D28: Determinants | E28: Properties, expansion, row operations, determinant of special matrices. | F28: Linear Algebra | GATE CSE Complete Course · GO Classes for GATE CS (instructor not named in playlist) | G28: Search this lecture ▶ | H28: Algorithms (DAA) (Day 10) | I28: GO-PDFs → Linear Algebra PYQs: 5-8 Qs (inside today's practice block) | J28: 40 | K28: Not Started
A29: 25 | B29: 46336 | C29: =TEXT(B29,"ddd") -> Tue | D29: Rank & inverse | E29: Rank via echelon form, inverse (adjoint & row ops), rank-nullity basics. | F29: Linear Algebra | GATE CSE Complete Course · GO Classes for GATE CS (instructor not named in playlist) | G29: Search this lecture ▶ | H29: Algorithms (DAA) (Day 11) | I29: GO-PDFs → Linear Algebra PYQs: 5-8 Qs (inside today's practice block) | J29: 40 | K29: Not Started
A30: 26 | B30: 46337 | C30: =TEXT(B30,"ddd") -> Wed | D30: Systems of linear equations | E30: Consistency, unique/infinite/no solutions, Gaussian elimination, homogeneous systems. | F30: Linear Algebra | GATE CSE Complete Course · GO Classes for GATE CS (instructor not named in playlist) | G30: Search this lecture ▶ | H30: Algorithms (DAA) (Day 12) | I30: GO-PDFs → Linear Algebra PYQs: 5-8 Qs (inside today's practice block) | J30: 40 | K30: Not Started
A31: 27 | B31: 46338 | C31: =TEXT(B31,"ddd") -> Thu | D31: Eigenvalues & eigenvectors | E31: Characteristic polynomial, computing eigenvalues/vectors, trace/determinant relations. | F31: Linear Algebra | GATE CSE Complete Course · GO Classes for GATE CS (instructor not named in playlist) | G31: Search this lecture ▶ | H31: Algorithms (DAA) (Day 13) | I31: GO-PDFs → Linear Algebra PYQs: 5-8 Qs (inside today's practice block) | J31: 40 | K31: Not Started
A32: 28 | B32: 46339 | C32: =TEXT(B32,"ddd") -> Fri | D32: Eigen properties: Cayley-Hamilton & diagonalisation | E32: Cayley-Hamilton theorem, diagonalisation, eigenvalues of special matrices. | F32: Linear Algebra | GATE CSE Complete Course · GO Classes for GATE CS (instructor not named in playlist) | G32: Search this lecture ▶ | H32: Compiler Design (Day 1) | I32: GO-PDFs → Linear Algebra PYQs: 5-8 Qs (inside today's practice block) | J32: 40 | K32: Not Started
A33: 29 | B33: 46340 | C33: =TEXT(B33,"ddd") -> Sat | D33: LU decomposition + LA problem-solving | E33: LU decomposition, solving systems with LU, mixed LA problems. | F33: Linear Algebra | GATE CSE Complete Course · GO Classes for GATE CS (instructor not named in playlist) | G33: Search this lecture ▶ | H33: Compiler Design (Day 2) | I33: GO-PDFs → Linear Algebra PYQs: 5-8 Qs (inside today's practice block) | J33: 40 | K33: Not Started | L33: Finish with 8-10 LA PYQs.
A34: 30 | B34: 46342 | C34: =TEXT(B34,"ddd") -> Mon | D34: Probability basics | E34: Sample space, axioms, equally likely outcomes, counting-based probability. | F34: Probability and Statistics for Engineering | GATE | gradeup · Channel: Algorithm Unlocked (instructor not named in playlist) | G34: Search this lecture ▶ | H34: Compiler Design (Day 3) | I34: GO-PDFs → Probability PYQs: 5-8 Qs (inside today's practice block) | J34: 40 | K34: Not Started
A35: 31 | B35: 46343 | C35: =TEXT(B35,"ddd") -> Tue | D35: Conditional probability & independence | E35: Conditional probability, multiplication rule, independent events. | F35: Probability and Statistics for Engineering | GATE | gradeup · Channel: Algorithm Unlocked (instructor not named in playlist) | G35: Search this lecture ▶ | H35: Compiler Design (Day 4) | I35: GO-PDFs → Probability PYQs: 5-8 Qs (inside today's practice block) | J35: 40 | K35: Not Started
A36: 32 | B36: 46344 | C36: =TEXT(B36,"ddd") -> Wed | D36: Bayes' theorem & total probability | E36: Total probability, Bayes' theorem, typical GATE problems. | F36: Probability and Statistics for Engineering | GATE | gradeup · Channel: Algorithm Unlocked (instructor not named in playlist) | G36: Search this lecture ▶ | H36: Compiler Design (Day 5) | I36: GO-PDFs → Probability PYQs: 5-8 Qs (inside today's practice block) | J36: 40 | K36: Not Started
A37: 33 | B37: 46345 | C37: =TEXT(B37,"ddd") -> Thu | D37: Random variables: PMF, PDF, CDF | E37: Discrete vs continuous RVs, PMF/PDF/CDF, computing probabilities. | F37: Probability and Statistics for Engineering | GATE | gradeup · Channel: Algorithm Unlocked (instructor not named in playlist) | G37: Search this lecture ▶ | H37: Compiler Design (Day 6) | I37: GO-PDFs → Probability PYQs: 5-8 Qs (inside today's practice block) | J37: 40 | K37: Not Started
A38: 34 | B38: 46346 | C38: =TEXT(B38,"ddd") -> Fri | D38: Expectation, variance & standard deviation | E38: E[X], Var(X), properties, linearity of expectation. | F38: Probability and Statistics for Engineering | GATE | gradeup · Channel: Algorithm Unlocked (instructor not named in playlist) | G38: Search this lecture ▶ | H38: Compiler Design (Day 7) | I38: GO-PDFs → Probability PYQs: 5-8 Qs (inside today's practice block) | J38: 40 | K38: Not Started
A39: 35 | B39: 46347 | C39: =TEXT(B39,"ddd") -> Sat | D39: Binomial distribution | E39: Bernoulli trials, binomial mean/variance, applications. | F39: Probability and Statistics for Engineering | GATE | gradeup · Channel: Algorithm Unlocked (instructor not named in playlist) | G39: Search this lecture ▶ | H39: Operating Systems (Day 1) | I39: GO-PDFs → Probability PYQs: 5-8 Qs (inside today's practice block) | J39: 40 | K39: Not Started
A40: 36 | B40: 46349 | C40: =TEXT(B40,"ddd") -> Mon | D40: Poisson distribution | E40: Poisson PMF, mean=variance, Poisson approximation to binomial. | F40: Probability and Statistics for Engineering | GATE | gradeup · Channel: Algorithm Unlocked (instructor not named in playlist) | G40: Search this lecture ▶ | H40: Operating Systems (Day 2) | I40: GO-PDFs → Probability PYQs: 5-8 Qs (inside today's practice block) | J40: 40 | K40: Not Started
A41: 37 | B41: 46350 | C41: =TEXT(B41,"ddd") -> Tue | D41: Uniform distribution | E41: Discrete & continuous uniform, mean, variance, probability from area. | F41: Probability and Statistics for Engineering | GATE | gradeup · Channel: Algorithm Unlocked (instructor not named in playlist) | G41: Search this lecture ▶ | H41: Operating Systems (Day 3) | I41: GO-PDFs → Probability PYQs: 5-8 Qs (inside today's practice block) | J41: 40 | K41: Not Started
A42: 38 | B42: 46351 | C42: =TEXT(B42,"ddd") -> Wed | D42: Exponential distribution | E42: Exponential PDF/CDF, memoryless property, mean & variance. | F42: Probability and Statistics for Engineering | GATE | gradeup · Channel: Algorithm Unlocked (instructor not named in playlist) | G42: Search this lecture ▶ | H42: Operating Systems (Day 4) | I42: GO-PDFs → Probability PYQs: 5-8 Qs (inside today's practice block) | J42: 40 | K42: Not Started
A43: 39 | B43: 46352 | C43: =TEXT(B43,"ddd") -> Thu | D43: Normal distribution | E43: Normal PDF, standard normal, z-scores, properties. | F43: Probability and Statistics for Engineering | GATE | gradeup · Channel: Algorithm Unlocked (instructor not named in playlist) | G43: Search this lecture ▶ | H43: Operating Systems (Day 5) | I43: GO-PDFs → Probability PYQs: 5-8 Qs (inside today's practice block) | J43: 35 | K43: Not Started
A44: 40 | B44: 46353 | C44: =TEXT(B44,"ddd") -> Fri | D44: Statistics: mean, median, mode & standard deviation | E44: Measures of central tendency & spread, grouped data. | F44: Introduction to probability and Statistics (NPTEL) · NPTEL-NOC IITM (instructor not named in playlist) | G44: Search this lecture ▶ | H44: Operating Systems (Day 6) | I44: GO-PDFs → Probability PYQs: 5-8 Qs (inside today's practice block) | J44: 35 | K44: Not Started
A45: 41 | B45: 46354 | C45: =TEXT(B45,"ddd") -> Sat | D45: Probability problem-solving: Bayes + distributions | E45: Mixed set of GATE-style questions across the probability chapter. | F45: Probability and Statistics for Engineering | GATE | gradeup · Channel: Algorithm Unlocked (instructor not named in playlist) | G45: Search this lecture ▶ | H45: Operating Systems (Day 7) | I45: GO-PDFs → Probability PYQs: 5-8 Qs (inside today's practice block) | J45: 35 | K45: Not Started | L45: Spend most of today on PYQs.
A46: 42 | B46: 46356 | C46: =TEXT(B46,"ddd") -> Mon | D46: Calculus: limits | E46: Limit laws, standard limits, L'Hôpital's rule, indeterminate forms. | F46: Calculus of One Variable - Joydeep Das | IIT Kanpur - NPTEL · Joydeep Das, IIT Kanpur | G46: Search this lecture ▶ | H46: Operating Systems (Day 8) | I46: GO-PDFs → Calculus PYQs: 5-8 Qs (inside today's practice block) | J46: 35 | K46: Not Started
A47: 43 | B47: 46357 | C47: =TEXT(B47,"ddd") -> Tue | D47: Calculus: continuity | E47: Continuity at a point/interval, types of discontinuity, intermediate value theorem. | F47: Calculus of One Variable - Joydeep Das | IIT Kanpur - NPTEL · Joydeep Das, IIT Kanpur | G47: Search this lecture ▶ | H47: Operating Systems (Day 9) | I47: GO-PDFs → Calculus PYQs: 5-8 Qs (inside today's practice block) | J47: 35 | K47: Not Started
A48: 44 | B48: 46358 | C48: =TEXT(B48,"ddd") -> Wed | D48: Calculus: differentiability | E48: Derivative definition, differentiability vs continuity, chain/product rules. | F48: Calculus of One Variable - Joydeep Das | IIT Kanpur - NPTEL · Joydeep Das, IIT Kanpur | G48: Search this lecture ▶ | H48: Operating Systems (Day 10) | I48: GO-PDFs → Calculus PYQs: 5-8 Qs (inside today's practice block) | J48: 35 | K48: Not Started
A49: 45 | B49: 46359 | C49: =TEXT(B49,"ddd") -> Thu | D49: Mean value theorems | E49: Rolle's theorem, Lagrange's MVT, applications. | F49: Calculus of One Variable - Joydeep Das | IIT Kanpur - NPTEL · Joydeep Das, IIT Kanpur | G49: Search this lecture ▶ | H49: Computer Networks (Day 1) | I49: GO-PDFs → Calculus PYQs: 5-8 Qs (inside today's practice block) | J49: 35 | K49: Not Started
A50: 46 | B50: 46360 | C50: =TEXT(B50,"ddd") -> Fri | D50: Maxima & minima | E50: Critical points, first/second derivative tests, optimisation. | F50: Calculus of One Variable - Joydeep Das | IIT Kanpur - NPTEL · Joydeep Das, IIT Kanpur | G50: Search this lecture ▶ | H50: Computer Networks (Day 2) | I50: GO-PDFs → Calculus PYQs: 5-8 Qs (inside today's practice block) | J50: 35 | K50: Not Started
A51: 47 | B51: 46361 | C51: =TEXT(B51,"ddd") -> Sat | D51: Integration I | E51: Indefinite integrals, substitution, integration by parts. | F51: Calculus of One Variable - Joydeep Das | IIT Kanpur - NPTEL · Joydeep Das, IIT Kanpur | G51: Search this lecture ▶ | H51: Computer Networks (Day 3) | I51: GO-PDFs → Calculus PYQs: 5-8 Qs (inside today's practice block) | J51: 35 | K51: Not Started
A52: 48 | B52: 46363 | C52: =TEXT(B52,"ddd") -> Mon | D52: Integration II | E52: Definite integrals, properties, area under curve. | F52: Calculus of One Variable - Joydeep Das | IIT Kanpur - NPTEL · Joydeep Das, IIT Kanpur | G52: Search this lecture ▶ | H52: Computer Networks (Day 4) | I52: GO-PDFs → Calculus PYQs: 5-8 Qs (inside today's practice block) | J52: 40 | K52: Not Started
A53: 49 | B53: 46364 | C53: =TEXT(B53,"ddd") -> Tue | D53: Integration III & calculus revision | E53: Improper integrals, applications; revise limits/continuity. | F53: Calculus Complete Playlist | Engineering Mathematics · GO Classes for GATE CS (instructor not named in playlist) | G53: Search this lecture ▶ | H53: Computer Networks (Day 5) | I53: GO-PDFs → Calculus PYQs: 5-8 Qs (inside today's practice block) | J53: 40 | K53: Not Started
A54: 50 | B54: 46365 | C54: =TEXT(B54,"ddd") -> Wed | D54: Calculus problem-solving with PYQs | E54: GO Classes calculus videos + calculus PYQs. | F54: Calculus Complete Playlist | Engineering Mathematics · GO Classes for GATE CS (instructor not named in playlist) | G54: Search this lecture ▶ | H54: Computer Networks (Day 6) | I54: GO-PDFs → Calculus PYQs: 5-8 Qs (inside today's practice block) | J54: 40 | K54: Not Started
A55: 51 | B55: 46366 | C55: =TEXT(B55,"ddd") -> Thu | D55: Discrete Maths consolidation (PYQs) | E55: Mixed discrete PYQs: logic, sets, relations, groups, graphs, combinatorics. | F55: Discrete Mathematics – Revision & PYQs video solutions (title not verified; from your resource PDF) · Not verified | G55: Search this lecture ▶ | H55: Computer Networks (Day 7) | I55: Timed PYQ set (use GO-PDFs / GO tests) | J55: 40 | K55: Not Started | L55: Open the PYQ video solutions and attempt each question first.
A56: 52 | B56: 46385 | C56: =TEXT(B56,"ddd") -> Tue | D56: LA + Probability + Calculus consolidation (PYQs) | E56: Mixed PYQs for the three remaining maths areas; fix weak spots. | F56: Linear Algebra | GATE CSE Complete Course · GO Classes for GATE CS (instructor not named in playlist) | G56: Search this lecture ▶ | H56: GATE recap day (29 Dec); CN Day 8 itself is on 21 Dec | I56: Timed PYQ set (use GO-PDFs / GO tests) | J56: 40 | K56: Not Started | L56: Use GO-PDFs topicwise PYQs for LA, Probability, Calculus.
I57: Total planned minutes | J57: =SUM(J5:J56) -> 1955

Sheet 8 Aptitude
A1: General Aptitude – daily 15-20 min warm-up (13 Oct – 29 Dec)
A2: Own status per day. 14 topics in 4 rounds: Round 1 = learn each topic, Round 2 = mixed practice, Round 3 = timed 10 Qs, Round 4 = full GA-style sets.
A4: Sources
A5: Verbal | C5: GATE Overflow – verbal aptitude lessons · GATE Overflow YouTube channel
A6: Quant & reasoning | C6: Complete Course on General Aptitude for GATE & ESE 2025 & 2026 (Unacademy) · Saurabh Thakur
A7: Resource video | C7: Aptitude resources, short notes & list of topics (video from your resource PDF) · as listed in your resource PDF
A8: Free tests | C8: GO Classes 2025 Monthly Quiz 1 – GA | D8: GO Classes Monthly Quiz 2 – GA | E8: GO Classes Monthly Quiz 3 – GA | F8: GO2017 Aptitude 1 | G8: General Aptitude Set 2
A10: Day # | B10: Date | C10: Day | D10: Round | E10: Topic | F10: What to do | G10: Source (click) | H10: Video search ▶ | I10: Planned min | J10: STATUS – aptitude only | K10: Notes
A11: 1 | B11: 46308 | C11: =TEXT(B11,"ddd") -> Tue | D11: Round 1 | E11: Percentages & ratios | F11: Learn: watch/skim the concept, note 2-3 tricks, solve 8-10 easy questions. | G11: Complete Course on General Aptitude for GATE & ESE 2025 & 2026 (Unacademy) · Saurabh Thakur | H11: Search this topic ▶ | I11: 15 | J11: Not Started
A12: 2 | B12: 46309 | C12: =TEXT(B12,"ddd") -> Wed | D12: Round 1 | E12: Time & work | F12: Learn: watch/skim the concept, note 2-3 tricks, solve 8-10 easy questions. | G12: Complete Course on General Aptitude for GATE & ESE 2025 & 2026 (Unacademy) · Saurabh Thakur | H12: Search this topic ▶ | I12: 15 | J12: Not Started
A13: 3 | B13: 46310 | C13: =TEXT(B13,"ddd") -> Thu | D13: Round 1 | E13: Speed, time & distance | F13: Learn: watch/skim the concept, note 2-3 tricks, solve 8-10 easy questions. | G13: Complete Course on General Aptitude for GATE & ESE 2025 & 2026 (Unacademy) · Saurabh Thakur | H13: Search this topic ▶ | I13: 15 | J13: Not Started
A14: 4 | B14: 46311 | C14: =TEXT(B14,"ddd") -> Fri | D14: Round 1 | E14: Profit/loss & averages | F14: Learn: watch/skim the concept, note 2-3 tricks, solve 8-10 easy questions. | G14: Complete Course on General Aptitude for GATE & ESE 2025 & 2026 (Unacademy) · Saurabh Thakur | H14: Search this topic ▶ | I14: 15 | J14: Not Started
A15: 5 | B15: 46312 | C15: =TEXT(B15,"ddd") -> Sat | D15: Round 1 | E15: Number series & sequences | F15: Learn: watch/skim the concept, note 2-3 tricks, solve 8-10 easy questions. | G15: Complete Course on General Aptitude for GATE & ESE 2025 & 2026 (Unacademy) · Saurabh Thakur | H15: Search this topic ▶ | I15: 15 | J15: Not Started
A16: 6 | B16: 46314 | C16: =TEXT(B16,"ddd") -> Mon | D16: Round 1 | E16: Basic counting & probability (aptitude level) | F16: Learn: watch/skim the concept, note 2-3 tricks, solve 8-10 easy questions. | G16: Complete Course on General Aptitude for GATE & ESE 2025 & 2026 (Unacademy) · Saurabh Thakur | H16: Search this topic ▶ | I16: 20 | J16: Not Started
A17: 7 | B17: 46315 | C17: =TEXT(B17,"ddd") -> Tue | D17: Round 1 | E17: Data interpretation (tables, bar charts) | F17: Learn: watch/skim the concept, note 2-3 tricks, solve 8-10 easy questions. | G17: Complete Course on General Aptitude for GATE & ESE 2025 & 2026 (Unacademy) · Saurabh Thakur | H17: Search this topic ▶ | I17: 20 | J17: Not Started
A18: 8 | B18: 46316 | C18: =TEXT(B18,"ddd") -> Wed | D18: Round 1 | E18: Verbal: tenses & subject-verb agreement | F18: Learn: watch/skim the concept, note 2-3 tricks, solve 8-10 easy questions. | G18: GATE Overflow – verbal aptitude lessons · GATE Overflow YouTube channel | H18: Search this topic ▶ | I18: 20 | J18: Not Started
A19: 9 | B19: 46317 | C19: =TEXT(B19,"ddd") -> Thu | D19: Round 1 | E19: Verbal: sentence completion & prepositions | F19: Learn: watch/skim the concept, note 2-3 tricks, solve 8-10 easy questions. | G19: GATE Overflow – verbal aptitude lessons · GATE Overflow YouTube channel | H19: Search this topic ▶ | I19: 20 | J19: Not Started
A20: 10 | B20: 46318 | C20: =TEXT(B20,"ddd") -> Fri | D20: Round 1 | E20: Verbal: synonyms, antonyms & idioms | F20: Learn: watch/skim the concept, note 2-3 tricks, solve 8-10 easy questions. | G20: GATE Overflow – verbal aptitude lessons · GATE Overflow YouTube channel | H20: Search this topic ▶ | I20: 20 | J20: Not Started
A21: 11 | B21: 46319 | C21: =TEXT(B21,"ddd") -> Sat | D21: Round 1 | E21: Reading comprehension (1 passage) | F21: Learn: watch/skim the concept, note 2-3 tricks, solve 8-10 easy questions. | G21: GATE Overflow – verbal aptitude lessons · GATE Overflow YouTube channel | H21: Search this topic ▶ | I21: 20 | J21: Not Started
A22: 12 | B22: 46321 | C22: =TEXT(B22,"ddd") -> Mon | D22: Round 1 | E22: Para-jumbles & sentence ordering | F22: Learn: watch/skim the concept, note 2-3 tricks, solve 8-10 easy questions. | G22: GATE Overflow – verbal aptitude lessons · GATE Overflow YouTube channel | H22: Search this topic ▶ | I22: 20 | J22: Not Started
... A62: 52 | B62: 46385 | C62: =TEXT(B62,"ddd") -> Tue | D62: Round 4 | E62: Verbal: synonyms, antonyms & idioms | F62: Full GA-style set: 10 mixed questions in 15 minutes from a GO aptitude test. | G62: GATE Overflow – verbal aptitude lessons · GATE Overflow YouTube channel | H62: Search this topic ▶ | I62: 20 | J62: Not Started
H63: Total planned minutes | I63: =SUM(I11:I62) -> 1015

Sheet Sunday Revision
A1: Sunday Revision & Test (Oct 18 – Dec 6)
A2: Sundays in Dec after the 6th are in 'Uni Exams & Wrap-up'. Format: 30 min notes → 90 min timed test (25 subject Qs + 10 maths Qs) → 60 min error log & redo.
A4: Date | B4: Day | C4: What to revise (last week's topics) | D4: Task 1: Notes (30 min) | E4: Task 2: Timed test (90 min) | F4: Task 3: Error log + redo (60 min) | G4: Planned hrs | H4: Status
A5: 46313 | B5: =TEXT(A5,"ddd") -> Sun | C5: Subjects: C Programming D1 (Basics: data types, operators, precedence); C Programming D2 (Control flow & I/O); C Programming D3 (Functions, recursion & storage classes); C Programming D4 (Arrays, strings & pointer basics); C Programming D5 (Advanced pointers, structs, unions, malloc, macros) Maths: Propositional logic I; Propositional logic II; Propositional logic III; First-order logic I; First-order logic II | D5: Re-read your handwritten notes/short notes for the topics at left | E5: 25 mixed PYQs from: C Programming + 10 Maths PYQs from this week's maths topics. Time yourself (~3 min per question). | F5: Write every wrong question in an Error Log (topic, why wrong, correct idea). Re-solve each once. | G5: 3 | H5: Not Started
A6: 46320 | B6: =TEXT(A6,"ddd") -> Sun | C6: Subjects: Data Structures D1 (Arrays & singly linked list); Data Structures D2 (Doubly/circular linked list & stacks); Data Structures D3 (Expression conversion, queues & deque); Data Structures D4 (Binary trees & traversals); Data Structures D5 (BST & AVL trees); Data Structures D6 (Binary heaps & priority queue) Maths: Sets; Relations I; Relations II; Functions; Partial orders & Hasse diagrams; Lattices | D6: Re-read your handwritten notes/short notes for the topics at left | E6: 25 mixed PYQs from: Data Structures + 10 Maths PYQs from this week's maths topics. Time yourself (~3 min per question). | F6: Write every wrong question in an Error Log (topic, why wrong, correct idea). Re-solve each once. | G6: 3 | H6: Not Started
A7: 46327 | B7: =TEXT(A7,"ddd") -> Sun | C7: Subjects: Data Structures D7 (Graph representation & basic traversals); Data Structures D8 (DS output-tracing & complexity PYQs); Data Structures D9 (DS full-topic test); Algorithms (DAA) D1 (Asymptotic notation & complexity analysis); Algorithms (DAA) D2 (Recurrence relations); Algorithms (DAA) D3 (Searching & basic sorting) Maths: Monoids, semigroups & groups; Subgroups, cyclic groups & Lagrange's theorem; Graph basics; Connectivity; Trees, Euler & Hamiltonian graphs; Planar graphs & matching | D7: Re-read your handwritten notes/short notes for the topics at left | E7: 25 mixed PYQs from: Data Structures, Algorithms (DAA) + 10 Maths PYQs from this week's maths topics. Time yourself (~3 min per question). | F7: Write every wrong question in an Error Log (topic, why wrong, correct idea). Re-solve each once. | G7: 3 | H7: Not Started
A8: 46334 | B8: =TEXT(A8,"ddd") -> Sun | C8: Diwali (approx.) – take it easy. Revise only: Algorithms (DAA) D4 (Merge, quick, heap sort & lower bounds); Algorithms (DAA) D5 (Hashing); Algorithms (DAA) D6 (Divide & conquer applications); Algorithms (DAA) D7 (Greedy algorithms); Algorithms (DAA) D8 (Graph traversals); Algorithms (DAA) D9 (Minimum spanning trees & union-find) | D8: Skim your notes lightly | E8: No test today | F8: Review the error log from last week (40 min) | G8: 1 | H8: Not Started
A9: 46341 | B9: =TEXT(A9,"ddd") -> Sun | C9: Subjects: Algorithms (DAA) D10 (Shortest paths); Algorithms (DAA) D11 (Dynamic programming I); Algorithms (DAA) D12 (Dynamic programming II); Algorithms (DAA) D13 (Uni-only: backtracking, branch & bound, NP-completeness); Compiler Design D1 (Compiler phases & lexical analysis); Compiler Design D2 (Parsing I: top-down & LL(1)) Maths: Determinants; Rank & inverse; Systems of linear equations; Eigenvalues & eigenvectors; Eigen properties; LU decomposition + LA problem-solving | D9: Re-read your handwritten notes/short notes for the topics at left | E9: 25 mixed PYQs from: Algorithms (DAA), Compiler Design + 10 Maths PYQs from this week's maths topics. Time yourself (~3 min per question). | F9: Write every wrong question in an Error Log (topic, why wrong, correct idea). Re-solve each once. | G9: 3 | H9: Not Started
A10: 46348 | B10: =TEXT(A10,"ddd") -> Sun | C10: Subjects: Compiler Design D3 (Parsing II: bottom-up, LR(0) & SLR(1)); Compiler Design D4 (Parsing III: CLR(1), LALR(1), operator precedence); Compiler Design D5 (Syntax-directed translation); Compiler Design D6 (Intermediate code & runtime environments); Compiler Design D7 (Code optimisation & data-flow analysis); Operating Systems D1 (OS basics, system calls & processes) Maths: Probability basics; Conditional probability & independence; Bayes' theorem & total probability; Random variables; Expectation, variance & standard deviation; Binomial distribution | D10: Re-read your handwritten notes/short notes for the topics at left | E10: 25 mixed PYQs from: Compiler Design, Operating Systems + 10 Maths PYQs from this week's maths topics. Time yourself (~3 min per question). | F10: Write every wrong question in an Error Log (topic, why wrong, correct idea). Re-solve each once. | G10: 3 | H10: Not Started
A11: 46355 | B11: =TEXT(A11,"ddd") -> Sun | C11: Subjects: Operating Systems D2 (Threads & inter-process communication); Operating Systems D3 (CPU scheduling I); Operating Systems D4 (CPU scheduling II); Operating Systems D5 (Process synchronisation I); Operating Systems D6 (Process synchronisation II); Operating Systems D7 (Deadlocks) Maths: Poisson distribution; Uniform distribution; Exponential distribution; Normal distribution; Statistics; Probability problem-solving | D11: Re-read your handwritten notes/short notes for the topics at left | E11: 25 mixed PYQs from: Operating Systems + 10 Maths PYQs from this week's maths topics. Time yourself (~3 min per question). | F11: Write every wrong question in an Error Log (topic, why wrong, correct idea). Re-solve each once. | G11: 3 | H11: Not Started
A12: 46362 | B12: =TEXT(A12,"ddd") -> Sun | C12: Subjects: Operating Systems D8 (Memory management: paging & segmentation); Operating Systems D9 (Virtual memory); Operating Systems D10 (File systems, disk scheduling & I/O); Computer Networks D1 (Layering, switching & performance metrics); Computer Networks D2 (Data link I: framing & error detection); Computer Networks D3 (Data link II: flow control & ARQ) Maths: Calculus; Calculus; Calculus; Mean value theorems; Maxima & minima; Integration I | D12: Re-read your handwritten notes/short notes for the topics at left | E12: 25 mixed PYQs from: Operating Systems, Computer Networks + 10 Maths PYQs from this week's maths topics. Time yourself (~3 min per question). | F12: Write every wrong question in an Error Log (topic, why wrong, correct idea). Re-solve each once. Bonus 30 min: open your IPU Software Engineering syllabus, list units, collect last 3 years' papers. | G12: 3 | H12: Not Started

Sheet Uni Exams & Wrap-up
A1: University Exam Prep & GATE Wrap-up (11 Dec – 31 Dec)
A2: Dates from your IPU end-term datesheet (5th sem, evening 2-5 PM). Software Engineering & Economics syllabi were not shared, so those days use typical topics – adjust to your IPU syllabus.
A4: Date | B4: Day | C4: Event | D4: Subject | E4: Focus | F4: Detailed plan | G4: Resources | H4: Planned hrs | I4: Status
A5: 46367 | B5: =TEXT(A5,"ddd") -> Fri | C5: Uni revision | D5: DAA | E5: DAA revision I: recurrences, sorting, D&C, hashing | F5: 1) Re-read your notes/cheat-sheet (30 min) 2) Solve last 3 yrs IPU DAA Q's on units 1-2 (90 min) 3) Redo wrong GATE PYQs (50 min) | G5: DAA backup playlist + your IPU DAA papers | H5: 3 | I5: Not Started
A6: 46368 | B6: =TEXT(A6,"ddd") -> Sat | C6: Uni revision | D6: DAA | E6: DAA revision II: greedy, DP, graph algorithms, NP/backtracking | F6: 1) Algorithm tables: complexity, MST, shortest paths (30 min) 2) Write DP/greedy answers in exam style (90 min) 3) IPU PYQs on NP/backtracking (50 min) | G6: DAA backup playlist + your IPU DAA papers | H6: 3 | I6: Not Started
A7: 46369 | B7: =TEXT(A7,"ddd") -> Sun | C7: Uni revision (Sunday) | D7: DAA | E7: DAA full timed mock paper | F7: 3 hours: attempt a complete IPU-pattern DAA paper in exam conditions, then evaluate and list weak topics. | G7: IPU DAA previous papers | H7: 3 | I7: Not Started
A8: 46370 | B8: =TEXT(A8,"ddd") -> Mon | C8: Uni revision | D8: DAA + CD | E8: DAA final polish + CD skim | F8: 1) DAA formula/algorithm sheet (60 min) 2) Quick DAA numericals (60 min) 3) Skim CD notes: parsing tables (50 min) | G8: Your notes | H8: 3 | I8: Not Started
A9: 46371 | B9: =TEXT(A9,"ddd") -> Tue | C9: UNI EXAM – DAA (2-5 PM) | D9: DAA | E9: EXAM DAY: CIC-311 Design & Analysis of Algorithms | F9: Morning only: 60 min light read of formula sheet. No new topics. Eat well, reach centre early. After exam: rest; CD revision tomorrow. | G9: Formula sheet | H9: 1 | I9: Not Started
A10: 46372 | B10: =TEXT(A10,"ddd") -> Wed | C10: Uni revision | D10: CD | E10: CD full revision day | F10: 1) Parsing practice: FIRST/FOLLOW, LL(1), LR tables (90 min) 2) SDT + ICG + code optimisation theory (60 min) 3) IPU CD PYQs (30 min) | G10: CD backup playlist (PYQ solutions) + IPU papers | H10: 3 | I10: Not Started
A11: 46373 | B11: =TEXT(A11,"ddd") -> Thu | C11: UNI EXAM – CD (2-5 PM) | D11: CD | E11: EXAM DAY: CIC-303 Compiler Design | F11: Morning only: 60 min – solve 2 parsing-table problems + review data-flow definitions. Then exam. | G11: Your notes | H11: 1 | I11: Not Started
A12: 46374 | B12: =TEXT(A12,"ddd") -> Fri | C12: Uni revision | D12: OS | E12: OS full revision day | F12: 1) Numericals: scheduling, Banker's, page replacement, paging/TLB (100 min) 2) Theory points: sync, file systems (50 min) 3) IPU OS PYQs (30 min) | G12: OS backup playlist (PYQ solutions) + IPU papers | H12: 3 | I12: Not Started
A13: 46375 | B13: =TEXT(A13,"ddd") -> Sat | C13: UNI EXAM – OS (2-5 PM) | D13: OS | E13: EXAM DAY: CIC-305 Operating Systems | F13: Morning only: 60 min – quick numerical warm-up (one problem each: SJF, Banker's, LRU). Then exam. | G13: Your notes | H13: 1 | I13: Not Started
A14: 46376 | B14: =TEXT(A14,"ddd") -> Sun | C14: Uni revision (Sunday) | D14: CN | E14: CN revision I: numericals | F14: 3 hours: subnetting/CIDR, sliding-window efficiency, CRC/Hamming, TCP congestion, distance-vector tables, ALOHA/CSMA-CD. | G14: CN backup playlist (PYQ solutions) | H14: 3 | I14: Not Started
A15: 46377 | B15: =TEXT(A15,"ddd") -> Mon | C15: Uni revision | D15: CN | E15: CN Day 8: Application layer + CN revision II: theory + IPU paper | F15: 1) CN Day 8 lecture – Application layer: DNS, HTTP, email (moved here from the original plan) (60 min) 2) Protocol/layer theory & uni-only topics (IPv6, security) (60 min) 3) IPU CN papers (40 min) 4) Formula sheet (20 min) | G15: IPU CN papers | H15: 3 | I15: Not Started
A16: 46378 | B16: =TEXT(A16,"ddd") -> Tue | C16: UNI EXAM – CN (2-5 PM) | D16: CN | E16: EXAM DAY: CIC-307 Computer Networks | F16: Morning only: 60 min – subnetting + TCP numerical warm-up. Then exam. | G16: Formula sheet | H16: 1 | I16: Not Started
... A25: 46387 | B25: =TEXT(A25,"ddd") -> Thu | C25: GATE consolidation | D25: All 6 covered sections | E25: Sectional mock + January plan | F25: 1) Timed 3h-style mock on the 6 covered sections (incl. Maths) (use a GATE2020 / GO test) (120 min) 2) Error analysis (40 min) 3) Draft January PYQ plan (20 min) | G25: GO free tests (see subject sheets) | H25: 3 | I25: Not Started

Sheet Playlist Directory
A1: Playlist Directory – every playlist, its teacher and uploader
A2: Titles, owners and video counts were read from YouTube. 'Instructor not named' = the playlist page only shows the channel. Individual video URLs could not be verified, so the day sheets use search links.
A4: Subject | B4: Role | C4: Playlist title | D4: Teacher / channel | E4: Uploaded by | F4: Videos | G4: Link
A5: C Programming | B5: Main | C5: C Programming | GATE 2024 | Vishvadeep Gothi Sir | D5: Vishvadeep Gothi Sir | E5: karthikeya pavan | F5: 40 | G5: Open playlist ▶
A6: C Programming | B6: Revision / PYQ solutions | C6: Introduction to Programming in C - Satyadev Nandakumar | IIT Kanpur: NPTEL | D6: Satyadev Nandakumar (IIT Kanpur) | E6: Rahul Madhavan | F6: 55 | G6: Open playlist ▶
A7: Data Structures | B7: Main | C7: Data Structures By Vishwadeep | D7: Vishwadeep Sir | E7: Kuldeep Siraswar (Kuldeep Saini) | F7: 40 | G7: Open playlist ▶
A8: Data Structures | B8: Revision / PYQ solutions | C8: Data Structure: GATE PYQs | GATE/ESE 2022 | Vishvadeep Sir | D8: Vishvadeep Sir (Unacademy Computer Science) | E8: Unacademy Computer Science | F8: 23 | G8: Open playlist ▶
A9: Data Structures | B9: Extra / NPTEL | C9: Computer Sc - Data Structures and Algorithms (NPTEL) | D9: Dr. Naveen Garg, IIT Delhi | E9: nptelhrd | F9: 36 | G9: Open playlist ▶
A10: Algorithms (DAA) | B10: Main | C10: DSA - Abdul Bari | D10: Abdul Bari | E10: Will Massey | F10: 163 | G10: Open playlist ▶
A11: Algorithms (DAA) | B11: Revision / PYQ solutions | C11: Algorithms - Revision, GATE PYQs Complete Analysis | GO Classes | Sachin Mittal | D11: Sachin Mittal (GO Classes) | E11: GO Classes for GATE CS | F11: 18 | G11: Open playlist ▶
A12: Algorithms (DAA) | B12: Extra / NPTEL | C12: Computer Sc - Design & Analysis of Algorithms (NPTEL) | D12: Prof. Abhiram Ranade, IIT Bombay | E12: nptelhrd | F12: 34 | G12: Open playlist ▶
A13: Compiler Design | B13: Main | C13: Compiler Design - GATE Computer Science Classes | D13: Prof. Ravindrababu Ravula | E13: Prof. Ravindrababu Ravula | F13: 49 | G13: Open playlist ▶
A14: Compiler Design | B14: Revision / PYQ solutions | C14: Compiler Design (GO Classes – GATE PYQs & revision) | D14: GO Classes for GATE CS (instructor not named in playlist) | E14: GO Classes for GATE CS | F14: 22 | G14: Open playlist ▶
A15: Compiler Design | B15: Extra / NPTEL | C15: Compiler Design : Intermediate Code & Code Optimization | Local Optimization | Dataflow Analysis | Liveness Analysis | D15: GO Classes for GATE CS (instructor not named in playlist) | E15: GO Classes for GATE CS | F15: 10 | G15: Open playlist ▶
A16: Compiler Design | B16: Extra / NPTEL | C16: CS3300 Compiler Design (IIT Madras) | D16: Dr. Rupesh Nasre, IIT Madras | E16: CSE IIT Madras | F16: 48 | G16: Open playlist ▶
... A31: Engineering Maths | B31: Statistics (NPTEL) | C31: Introduction to probability and Statistics (NPTEL) | D31: NPTEL-NOC IITM (instructor not named in playlist) | E31: NPTEL-NOC IITM | F31: 21 | G31: Open playlist ▶
A32: Engineering Maths | B32: Calculus (NPTEL) | C32: Calculus of One Variable - Joydeep Das | IIT Kanpur - NPTEL | D32: Joydeep Das, IIT Kanpur | E32: (not shown) | F32: — | G32: Open playlist ▶
A33: Engineering Maths | B33: Calculus (GO Classes) | C33: Calculus Complete Playlist | Engineering Mathematics | D33: GO Classes for GATE CS (instructor not named in playlist) | E33: GO Classes for GATE CS | F33: 5 | G33: Open playlist ▶
A34: Engineering Maths | B34: Discrete – PYQ revision | C34: Discrete Mathematics – Revision & PYQs video solutions (title not verified; from your resource PDF) | D34: Not verified | E34: (not verified) | F34: — | G34: Open playlist ▶
A35: General Aptitude | B35: Aptitude – verbal | C35: GATE Overflow – verbal aptitude lessons | D35: GATE Overflow YouTube channel | E35: — | F35: — | G35: Open playlist ▶
A36: General Aptitude | B36: Aptitude – quant & reasoning (Unacademy course, not YouTube; may need login) | C36: Complete Course on General Aptitude for GATE & ESE 2025 & 2026 (Unacademy) | D36: Saurabh Thakur | E36: — | F36: — | G36: Open playlist ▶
A37: General Aptitude | B37: Aptitude – resource video | C37: Aptitude resources, short notes & list of topics (video from your resource PDF) | D37: as listed in your resource PDF | E37: — | F37: — | G37: Open playlist ▶
